[
  {
    "id": "boston-sweden-scandinavian-cultural-center-library",
    "slug": "boston-sweden-scandinavian-cultural-center-library",
    "name": "Scandinavian Cultural Center & Library",
    "description": "Scandinavian Cultural Center & Library is a Sweden restaurant in Boston.",
    "address": "206 Waltham St, West Newton, MA 02465, USA",
    "city": "boston",
    "state": "MA",
    "postalCode": "02465",
    "lat": 42.359831299999996,
    "lng": -71.22118139999999,
    "borough": "Manhattan",
    "neighborhood": "Boston",
    "website": "http://www.scandicenter.org/",
    "googleMapsUrl": "https://maps.google.com/?cid=7728922942975686667&g_mp=Cidnb29nbGUubWFwcy5wbGFjZXMudjEuUGxhY2VzLlNlYXJjaFRleHQQAhgEIAA",
    "venueTypes": [
      "cultural_center"
    ],
    "associatedCountries": [
      "sweden"
    ],
    "likelySupporterCountry": "sweden",
    "venueIntent": "cultural_restaurant",
    "cuisineTags": [
      "sweden",
      "sweden cuisine"
    ],
    "atmosphereTags": [
      "casual",
      "authentic-food"
    ],
    "showsSoccer": false,
    "openNow": false,
    "priceLevel": 3,
    "rating": 4.9,
    "reviewCount": 38,
    "numberOfScreens": 1,
    "hasProjector": false,
    "hasOutdoorViewing": false,
    "familyFriendly": true,
    "standingRoomFriendly": false,
    "privateEventsAvailable": true,
    "goodForGroups": false,
    "acceptsReservations": true,
    "reservationType": "external_url",
    "reservationUrl": "http://www.scandicenter.org/",
    "approximateCapacity": 45,
    "capacityBucket": "30_60",
    "capacityConfidence": "estimated",
    "sourceType": "official_api",
    "sourceName": "Google Places",
    "sourceExternalId": "ChIJa8BxhumC44kRC7hukHemQms",
    "sourceConfidence": 0.92,
    "verificationStatus": "imported",
    "isRealVenue": true,
    "isFeatured": false,
    "isOfficialFanHub": false,
    "gameDayScore": 5.997000000000001,
    "fanLikelihoodScore": 6.797000000000001,
    "editorialBoost": 0.15,
    "editorialNotes": "Imported from Google Places with name match: scandinavian.",
    "supporterNotes": "Country assignment verified via name match.",
    "imageUrls": [],
    "createdAt": "2026-04-25T05:35:28.267Z",
    "updatedAt": "2026-04-25T05:49:06.438Z"
  },
  {
    "id": "boston-sweden-scandinavian-living-center",
    "slug": "boston-sweden-scandinavian-living-center",
    "name": "Scandinavian Living Center",
    "description": "Scandinavian Living Center is a Sweden restaurant in Boston.",
    "address": "206 Waltham St, Newton, MA 02465, USA",
    "city": "boston",
    "state": "MA",
    "postalCode": "02465",
    "lat": 42.359831799999995,
    "lng": -71.221296,
    "borough": "Manhattan",
    "neighborhood": "Boston",
    "website": "http://www.slcenter.org/",
    "googleMapsUrl": "https://maps.google.com/?cid=3845895528566201849&g_mp=Cidnb29nbGUubWFwcy5wbGFjZXMudjEuUGxhY2VzLlNlYXJjaFRleHQQAhgEIAA",
    "venueTypes": [
      "cultural_center"
    ],
    "associatedCountries": [
      "sweden"
    ],
    "likelySupporterCountry": "sweden",
    "venueIntent": "cultural_restaurant",
    "cuisineTags": [
      "sweden",
      "sweden cuisine"
    ],
    "atmosphereTags": [
      "casual",
      "authentic-food"
    ],
    "showsSoccer": false,
    "openNow": false,
    "priceLevel": 3,
    "rating": 4.6,
    "reviewCount": 58,
    "numberOfScreens": 1,
    "hasProjector": false,
    "hasOutdoorViewing": false,
    "familyFriendly": true,
    "standingRoomFriendly": false,
    "privateEventsAvailable": true,
    "goodForGroups": false,
    "acceptsReservations": true,
    "reservationType": "external_url",
    "reservationUrl": "http://www.slcenter.org/",
    "approximateCapacity": 45,
    "capacityBucket": "30_60",
    "capacityConfidence": "estimated",
    "sourceType": "official_api",
    "sourceName": "Google Places",
    "sourceExternalId": "ChIJdecJhumC44kR-Z1zV5tdXzU",
    "sourceConfidence": 0.92,
    "verificationStatus": "imported",
    "isRealVenue": true,
    "isFeatured": false,
    "isOfficialFanHub": false,
    "gameDayScore": 5.732,
    "fanLikelihoodScore": 6.532,
    "editorialBoost": 0.15,
    "editorialNotes": "Imported from Google Places with name match: scandinavian.",
    "supporterNotes": "Country assignment verified via name match.",
    "imageUrls": [],
    "createdAt": "2026-04-25T05:35:28.267Z",
    "updatedAt": "2026-04-25T05:49:06.438Z"
  },
  {
    "id": "boston-sweden-scandinavian-library-info",
    "slug": "boston-sweden-scandinavian-library-info",
    "name": "Scandinavian Library & Info",
    "description": "Scandinavian Library & Info is a Sweden restaurant in Boston.",
    "address": "206 Waltham St, Newton, MA 02465, USA",
    "city": "boston",
    "state": "MA",
    "postalCode": "02465",
    "lat": 42.359831799999995,
    "lng": -71.221296,
    "borough": "Manhattan",
    "neighborhood": "Boston",
    "website": "http://scandinavianlibrary.org/",
    "googleMapsUrl": "https://maps.google.com/?cid=9475828576987136476&g_mp=Cidnb29nbGUubWFwcy5wbGFjZXMudjEuUGxhY2VzLlNlYXJjaFRleHQQAhgEIAA",
    "venueTypes": [],
    "associatedCountries": [
      "sweden"
    ],
    "likelySupporterCountry": "sweden",
    "venueIntent": "cultural_restaurant",
    "cuisineTags": [
      "sweden",
      "sweden cuisine"
    ],
    "atmosphereTags": [
      "casual",
      "authentic-food"
    ],
    "showsSoccer": false,
    "openNow": true,
    "priceLevel": 3,
    "rating": 5,
    "reviewCount": 1,
    "numberOfScreens": 1,
    "hasProjector": false,
    "hasOutdoorViewing": false,
    "familyFriendly": true,
    "standingRoomFriendly": false,
    "privateEventsAvailable": true,
    "goodForGroups": false,
    "acceptsReservations": true,
    "reservationType": "external_url",
    "reservationUrl": "http://scandinavianlibrary.org/",
    "approximateCapacity": 45,
    "capacityBucket": "30_60",
    "capacityConfidence": "estimated",
    "sourceType": "official_api",
    "sourceName": "Google Places",
    "sourceExternalId": "ChIJdecJhumC44kR3EHQu-LngIM",
    "sourceConfidence": 0.92,
    "verificationStatus": "imported",
    "isRealVenue": true,
    "isFeatured": false,
    "isOfficialFanHub": false,
    "gameDayScore": 5.964,
    "fanLikelihoodScore": 6.764,
    "editorialBoost": 0.15,
    "editorialNotes": "Imported from Google Places with name match: scandinavian.",
    "supporterNotes": "Country assignment verified via name match.",
    "imageUrls": [],
    "createdAt": "2026-04-25T05:35:28.267Z",
    "updatedAt": "2026-04-25T05:49:06.438Z"
  }
]