[
  {
    "id": "las-vegas-ir-iran-kickers-gaming-sports-bar",
    "slug": "las-vegas-ir-iran-kickers-gaming-sports-bar",
    "name": "Kickers Gaming & Sports Bar",
    "description": "Kickers Gaming & Sports Bar in Las Vegas for IR Iran.",
    "address": "931 Las Vegas Blvd N, Las Vegas, NV 89101, USA",
    "city": "Las Vegas",
    "state": "NV",
    "postalCode": "89101",
    "lat": 36.182106399999995,
    "lng": -115.1345817,
    "borough": "Manhattan",
    "neighborhood": "Las Vegas",
    "website": "https://www.kickerslv.com/",
    "googleMapsUrl": "https://maps.google.com/?cid=1756902596098999050&g_mp=Cidnb29nbGUubWFwcy5wbGFjZXMudjEuUGxhY2VzLlNlYXJjaFRleHQQAhgEIAA",
    "venueTypes": [
      "bar",
      "supporter_club"
    ],
    "associatedCountries": [
      "ir-iran"
    ],
    "likelySupporterCountry": "ir-iran",
    "venueIntent": "sports_bar",
    "cuisineTags": [
      "ir iran",
      "ir iran cuisine"
    ],
    "atmosphereTags": [
      "watch-party",
      "loud",
      "big-groups"
    ],
    "showsSoccer": true,
    "openNow": true,
    "priceLevel": 2,
    "rating": 4.7,
    "reviewCount": 168,
    "numberOfScreens": 5,
    "hasProjector": true,
    "hasOutdoorViewing": true,
    "familyFriendly": false,
    "standingRoomFriendly": true,
    "privateEventsAvailable": true,
    "goodForGroups": true,
    "acceptsReservations": true,
    "reservationType": "external_url",
    "reservationUrl": "https://www.kickerslv.com/",
    "approximateCapacity": 120,
    "capacityBucket": "100_200",
    "capacityConfidence": "estimated",
    "sourceType": "official_api",
    "sourceName": "Google Places",
    "sourceExternalId": "ChIJNzqd12fDyIARCkNxSZrFYRg",
    "sourceConfidence": 0.92,
    "verificationStatus": "imported",
    "isRealVenue": true,
    "isFeatured": false,
    "isOfficialFanHub": false,
    "gameDayScore": 7.436999999999999,
    "fanLikelihoodScore": 8.237,
    "editorialBoost": 0.15,
    "imageUrls": [],
    "createdAt": "2026-04-24T03:10:36.450Z",
    "updatedAt": "2026-04-24T03:10:36.450Z"
  },
  {
    "id": "las-vegas-ir-iran-hola-habibi",
    "slug": "las-vegas-ir-iran-hola-habibi",
    "name": "Hola Habibi",
    "description": "Hola Habibi in Las Vegas for IR Iran.",
    "address": "1115 S Casino Center Blvd, Las Vegas, NV 89104, USA",
    "city": "Las Vegas",
    "state": "NV",
    "postalCode": "89104",
    "lat": 36.1580364,
    "lng": -115.15215040000001,
    "borough": "Manhattan",
    "neighborhood": "Las Vegas",
    "website": "http://www.holahabibi.vegas/",
    "googleMapsUrl": "https://maps.google.com/?cid=1248169195260308603&g_mp=Cidnb29nbGUubWFwcy5wbGFjZXMudjEuUGxhY2VzLlNlYXJjaFRleHQQAhgEIAA",
    "venueTypes": [
      "bar"
    ],
    "associatedCountries": [
      "ir-iran"
    ],
    "likelySupporterCountry": "ir-iran",
    "venueIntent": "sports_bar",
    "cuisineTags": [
      "ir iran",
      "ir iran cuisine"
    ],
    "atmosphereTags": [
      "watch-party",
      "loud",
      "big-groups"
    ],
    "showsSoccer": true,
    "openNow": true,
    "priceLevel": 2,
    "rating": 4.6,
    "reviewCount": 83,
    "numberOfScreens": 5,
    "hasProjector": true,
    "hasOutdoorViewing": true,
    "familyFriendly": false,
    "standingRoomFriendly": true,
    "privateEventsAvailable": true,
    "goodForGroups": true,
    "acceptsReservations": true,
    "reservationType": "external_url",
    "reservationUrl": "http://www.holahabibi.vegas/",
    "approximateCapacity": 70,
    "capacityBucket": "60_100",
    "capacityConfidence": "estimated",
    "sourceType": "official_api",
    "sourceName": "Google Places",
    "sourceExternalId": "ChIJw1XFQ2_DyIARe2wTH0VjUhE",
    "sourceConfidence": 0.92,
    "verificationStatus": "imported",
    "isRealVenue": true,
    "isFeatured": false,
    "isOfficialFanHub": false,
    "gameDayScore": 6.981999999999999,
    "fanLikelihoodScore": 7.781999999999999,
    "editorialBoost": 0.15,
    "imageUrls": [],
    "createdAt": "2026-04-24T03:10:36.450Z",
    "updatedAt": "2026-04-24T03:10:36.450Z"
  },
  {
    "id": "las-vegas-ir-iran-foreign-exchange-lounge",
    "slug": "las-vegas-ir-iran-foreign-exchange-lounge",
    "name": "Foreign Exchange Lounge",
    "description": "Foreign Exchange Lounge in Las Vegas for IR Iran.",
    "address": "200 Hoover Ave STE 150, Las Vegas, NV 89101, USA",
    "city": "Las Vegas",
    "state": "NV",
    "postalCode": "89101",
    "lat": 36.161510799999995,
    "lng": -115.14964239999999,
    "borough": "Manhattan",
    "neighborhood": "Las Vegas",
    "googleMapsUrl": "https://maps.google.com/?cid=17539746795841063391&g_mp=Cidnb29nbGUubWFwcy5wbGFjZXMudjEuUGxhY2VzLlNlYXJjaFRleHQQAhgEIAA",
    "venueTypes": [
      "bar"
    ],
    "associatedCountries": [
      "ir-iran"
    ],
    "likelySupporterCountry": "ir-iran",
    "venueIntent": "sports_bar",
    "cuisineTags": [
      "ir iran",
      "ir iran cuisine"
    ],
    "atmosphereTags": [
      "watch-party",
      "loud",
      "big-groups"
    ],
    "showsSoccer": true,
    "openNow": true,
    "priceLevel": 2,
    "rating": 4.9,
    "reviewCount": 99,
    "numberOfScreens": 5,
    "hasProjector": true,
    "hasOutdoorViewing": true,
    "familyFriendly": false,
    "standingRoomFriendly": true,
    "privateEventsAvailable": false,
    "goodForGroups": true,
    "acceptsReservations": false,
    "reservationType": "none",
    "approximateCapacity": 70,
    "capacityBucket": "60_100",
    "capacityConfidence": "estimated",
    "sourceType": "official_api",
    "sourceName": "Google Places",
    "sourceExternalId": "ChIJudcdBQDDyIAR3wlnAMiyafM",
    "sourceConfidence": 0.92,
    "verificationStatus": "imported",
    "isRealVenue": true,
    "isFeatured": false,
    "isOfficialFanHub": false,
    "gameDayScore": 7.391,
    "fanLikelihoodScore": 8.191,
    "editorialBoost": 0.15,
    "imageUrls": [],
    "createdAt": "2026-04-24T03:10:36.450Z",
    "updatedAt": "2026-04-24T03:10:36.450Z"
  },
  {
    "id": "las-vegas-ir-iran-stadia-bar-at-caesars-palace-las-vegas",
    "slug": "las-vegas-ir-iran-stadia-bar-at-caesars-palace-las-vegas",
    "name": "Stadia Bar at Caesars Palace Las Vegas",
    "description": "Stadia Bar at Caesars Palace Las Vegas in Las Vegas for IR Iran.",
    "address": "3570 S Las Vegas Blvd, Las Vegas, NV 89109, USA",
    "city": "Las Vegas",
    "state": "NV",
    "postalCode": "89109",
    "lat": 36.117913,
    "lng": -115.1757996,
    "borough": "Manhattan",
    "neighborhood": "Las Vegas",
    "website": "https://www.caesars.com/caesars-palace/things-to-do/nightlife/stadia?utm_campaign=gmb&utm_source=google&utm_medium=local&utm_term=CLV102&utm_content=bar&y_source=1_MjQyNzU3MDgtNzE1LWxvY2F0aW9uLndlYnNpdGU%3D",
    "googleMapsUrl": "https://maps.google.com/?cid=14701452505456095450&g_mp=Cidnb29nbGUubWFwcy5wbGFjZXMudjEuUGxhY2VzLlNlYXJjaFRleHQQAhgEIAA",
    "venueTypes": [
      "bar",
      "supporter_club"
    ],
    "associatedCountries": [
      "ir-iran"
    ],
    "likelySupporterCountry": "ir-iran",
    "venueIntent": "sports_bar",
    "cuisineTags": [
      "ir iran",
      "ir iran cuisine"
    ],
    "atmosphereTags": [
      "watch-party",
      "loud",
      "big-groups"
    ],
    "showsSoccer": true,
    "openNow": true,
    "priceLevel": 2,
    "rating": 3.6,
    "reviewCount": 34,
    "numberOfScreens": 5,
    "hasProjector": true,
    "hasOutdoorViewing": true,
    "familyFriendly": false,
    "standingRoomFriendly": true,
    "privateEventsAvailable": true,
    "goodForGroups": true,
    "acceptsReservations": true,
    "reservationType": "external_url",
    "reservationUrl": "https://www.caesars.com/caesars-palace/things-to-do/nightlife/stadia?utm_campaign=gmb&utm_source=google&utm_medium=local&utm_term=CLV102&utm_content=bar&y_source=1_MjQyNzU3MDgtNzE1LWxvY2F0aW9uLndlYnNpdGU%3D",
    "approximateCapacity": 120,
    "capacityBucket": "100_200",
    "capacityConfidence": "estimated",
    "sourceType": "official_api",
    "sourceName": "Google Places",
    "sourceExternalId": "ChIJBXIcTFLFyIAR2rD8fSkNBsw",
    "sourceConfidence": 0.92,
    "verificationStatus": "imported",
    "isRealVenue": true,
    "isFeatured": false,
    "isOfficialFanHub": false,
    "gameDayScore": 5.636,
    "fanLikelihoodScore": 6.436,
    "editorialBoost": 0.15,
    "imageUrls": [],
    "createdAt": "2026-04-24T03:10:36.450Z",
    "updatedAt": "2026-04-24T03:10:36.450Z"
  },
  {
    "id": "las-vegas-ir-iran-crown-anchor-british-pub",
    "slug": "las-vegas-ir-iran-crown-anchor-british-pub",
    "name": "Crown & Anchor British Pub",
    "description": "Crown & Anchor British Pub in Las Vegas for IR Iran.",
    "address": "4755 W Spring Mountain Rd, Las Vegas, NV 89102, USA",
    "city": "Las Vegas",
    "state": "NV",
    "postalCode": "89102",
    "lat": 36.1260531,
    "lng": -115.2059627,
    "borough": "Manhattan",
    "neighborhood": "Las Vegas",
    "website": "https://www.crownandanchorlv.com/",
    "googleMapsUrl": "https://maps.google.com/?cid=10895206341828913011&g_mp=Cidnb29nbGUubWFwcy5wbGFjZXMudjEuUGxhY2VzLlNlYXJjaFRleHQQAhgEIAA",
    "venueTypes": [
      "bar",
      "supporter_club"
    ],
    "associatedCountries": [
      "ir-iran"
    ],
    "likelySupporterCountry": "ir-iran",
    "venueIntent": "sports_bar",
    "cuisineTags": [
      "ir iran",
      "ir iran cuisine"
    ],
    "atmosphereTags": [
      "watch-party",
      "loud",
      "big-groups"
    ],
    "showsSoccer": true,
    "openNow": true,
    "priceLevel": 2,
    "rating": 4.3,
    "reviewCount": 744,
    "numberOfScreens": 5,
    "hasProjector": true,
    "hasOutdoorViewing": true,
    "familyFriendly": false,
    "standingRoomFriendly": true,
    "privateEventsAvailable": true,
    "goodForGroups": true,
    "acceptsReservations": true,
    "reservationType": "external_url",
    "reservationUrl": "https://www.crownandanchorlv.com/",
    "approximateCapacity": 120,
    "capacityBucket": "100_200",
    "capacityConfidence": "estimated",
    "sourceType": "official_api",
    "sourceName": "Google Places",
    "sourceExternalId": "ChIJAVeIprDGyIARc6dLT3GMM5c",
    "sourceConfidence": 0.92,
    "verificationStatus": "imported",
    "isRealVenue": true,
    "isFeatured": false,
    "isOfficialFanHub": false,
    "gameDayScore": 7.805,
    "fanLikelihoodScore": 8.605,
    "editorialBoost": 0.15,
    "imageUrls": [],
    "createdAt": "2026-04-24T03:10:36.450Z",
    "updatedAt": "2026-04-24T03:10:36.450Z"
  },
  {
    "id": "las-vegas-ir-iran-la-mojarra-loca-grill",
    "slug": "las-vegas-ir-iran-la-mojarra-loca-grill",
    "name": "La Mojarra Loca Grill",
    "description": "La Mojarra Loca Grill in Las Vegas for IR Iran.",
    "address": "2797 S Maryland Pkwy, Las Vegas, NV 89109, USA",
    "city": "Las Vegas",
    "state": "NV",
    "postalCode": "89109",
    "lat": 36.137799199999996,
    "lng": -115.137228,
    "borough": "Manhattan",
    "neighborhood": "Las Vegas",
    "website": "http://lamojarralocalasvegas.net/",
    "googleMapsUrl": "https://maps.google.com/?cid=13574245741343439975&g_mp=Cidnb29nbGUubWFwcy5wbGFjZXMudjEuUGxhY2VzLlNlYXJjaFRleHQQAhgEIAA",
    "venueTypes": [
      "bar",
      "restaurant"
    ],
    "associatedCountries": [
      "ir-iran"
    ],
    "likelySupporterCountry": "ir-iran",
    "venueIntent": "sports_bar",
    "cuisineTags": [
      "ir iran",
      "ir iran cuisine"
    ],
    "atmosphereTags": [
      "watch-party",
      "loud",
      "big-groups"
    ],
    "showsSoccer": true,
    "openNow": true,
    "priceLevel": 2,
    "rating": 4.5,
    "reviewCount": 6924,
    "numberOfScreens": 5,
    "hasProjector": true,
    "hasOutdoorViewing": true,
    "familyFriendly": false,
    "standingRoomFriendly": true,
    "privateEventsAvailable": true,
    "goodForGroups": true,
    "acceptsReservations": true,
    "reservationType": "external_url",
    "reservationUrl": "http://lamojarralocalasvegas.net/",
    "approximateCapacity": 70,
    "capacityBucket": "60_100",
    "capacityConfidence": "estimated",
    "sourceType": "official_api",
    "sourceName": "Google Places",
    "sourceExternalId": "ChIJp_tp_YjEyIARZ3yiEpVoYbw",
    "sourceConfidence": 0.92,
    "verificationStatus": "imported",
    "isRealVenue": true,
    "isFeatured": true,
    "isOfficialFanHub": false,
    "gameDayScore": 8.035,
    "fanLikelihoodScore": 8.835,
    "editorialBoost": 0.15,
    "imageUrls": [],
    "createdAt": "2026-04-24T03:10:36.450Z",
    "updatedAt": "2026-04-24T03:10:36.450Z"
  },
  {
    "id": "las-vegas-ir-iran-teikerizi-sports-bar-and-lounge",
    "slug": "las-vegas-ir-iran-teikerizi-sports-bar-and-lounge",
    "name": "Teikerizi Sports Bar and Lounge",
    "description": "Teikerizi Sports Bar and Lounge in Las Vegas for IR Iran.",
    "address": "4465 E Sahara Ave, Las Vegas, NV 89104, USA",
    "city": "Las Vegas",
    "state": "NV",
    "postalCode": "89104",
    "lat": 36.143967499999995,
    "lng": -115.07741820000001,
    "borough": "Manhattan",
    "neighborhood": "Las Vegas",
    "website": "https://www.instagram.com/",
    "googleMapsUrl": "https://maps.google.com/?cid=4859227156755205977&g_mp=Cidnb29nbGUubWFwcy5wbGFjZXMudjEuUGxhY2VzLlNlYXJjaFRleHQQAhgEIAA",
    "venueTypes": [
      "bar",
      "restaurant",
      "supporter_club"
    ],
    "associatedCountries": [
      "ir-iran"
    ],
    "likelySupporterCountry": "ir-iran",
    "venueIntent": "sports_bar",
    "cuisineTags": [
      "ir iran",
      "ir iran cuisine"
    ],
    "atmosphereTags": [
      "watch-party",
      "loud",
      "big-groups"
    ],
    "showsSoccer": true,
    "openNow": true,
    "priceLevel": 2,
    "rating": 3.8,
    "reviewCount": 52,
    "numberOfScreens": 5,
    "hasProjector": true,
    "hasOutdoorViewing": true,
    "familyFriendly": false,
    "standingRoomFriendly": true,
    "privateEventsAvailable": true,
    "goodForGroups": true,
    "acceptsReservations": true,
    "reservationType": "external_url",
    "reservationUrl": "https://www.instagram.com/",
    "approximateCapacity": 120,
    "capacityBucket": "100_200",
    "capacityConfidence": "estimated",
    "sourceType": "official_api",
    "sourceName": "Google Places",
    "sourceExternalId": "ChIJaYsopP_byIARWU9TkVpxb0M",
    "sourceConfidence": 0.92,
    "verificationStatus": "imported",
    "isRealVenue": true,
    "isFeatured": false,
    "isOfficialFanHub": false,
    "gameDayScore": 5.938,
    "fanLikelihoodScore": 6.7379999999999995,
    "editorialBoost": 0.15,
    "imageUrls": [],
    "createdAt": "2026-04-24T03:10:36.450Z",
    "updatedAt": "2026-04-24T03:10:36.450Z"
  },
  {
    "id": "las-vegas-ir-iran-the-island-bar-and-grill",
    "slug": "las-vegas-ir-iran-the-island-bar-and-grill",
    "name": "The Island Bar and Grill",
    "description": "The Island Bar and Grill in Las Vegas for IR Iran.",
    "address": "2660 S Maryland Pkwy, Las Vegas, NV 89104, USA",
    "city": "Las Vegas",
    "state": "NV",
    "postalCode": "89104",
    "lat": 36.141243599999996,
    "lng": -115.13578499999998,
    "borough": "Manhattan",
    "neighborhood": "Las Vegas",
    "website": "https://www.theislandbargrill.com/home",
    "googleMapsUrl": "https://maps.google.com/?cid=6745341192714932748&g_mp=Cidnb29nbGUubWFwcy5wbGFjZXMudjEuUGxhY2VzLlNlYXJjaFRleHQQAhgEIAA",
    "venueTypes": [
      "bar"
    ],
    "associatedCountries": [
      "ir-iran"
    ],
    "likelySupporterCountry": "ir-iran",
    "venueIntent": "sports_bar",
    "cuisineTags": [
      "ir iran",
      "ir iran cuisine"
    ],
    "atmosphereTags": [
      "watch-party",
      "loud",
      "big-groups"
    ],
    "showsSoccer": true,
    "openNow": true,
    "priceLevel": 2,
    "rating": 4.5,
    "reviewCount": 89,
    "numberOfScreens": 5,
    "hasProjector": true,
    "hasOutdoorViewing": true,
    "familyFriendly": false,
    "standingRoomFriendly": true,
    "privateEventsAvailable": true,
    "goodForGroups": true,
    "acceptsReservations": true,
    "reservationType": "external_url",
    "reservationUrl": "https://www.theislandbargrill.com/home",
    "approximateCapacity": 70,
    "capacityBucket": "60_100",
    "capacityConfidence": "estimated",
    "sourceType": "official_api",
    "sourceName": "Google Places",
    "sourceExternalId": "ChIJDQ8QRFXFyIARDFKVkBNEnF0",
    "sourceConfidence": 0.92,
    "verificationStatus": "imported",
    "isRealVenue": true,
    "isFeatured": false,
    "isOfficialFanHub": false,
    "gameDayScore": 6.891,
    "fanLikelihoodScore": 7.691,
    "editorialBoost": 0.15,
    "imageUrls": [],
    "createdAt": "2026-04-24T03:10:36.450Z",
    "updatedAt": "2026-04-24T03:10:36.450Z"
  },
  {
    "id": "las-vegas-ir-iran-the-spot-lv",
    "slug": "las-vegas-ir-iran-the-spot-lv",
    "name": "The Spot LV",
    "description": "The Spot LV in Las Vegas for IR Iran.",
    "address": "8410 W Desert Inn Rd, Las Vegas, NV 89117, USA",
    "city": "Las Vegas",
    "state": "NV",
    "postalCode": "89117",
    "lat": 36.1298163,
    "lng": -115.2745441,
    "borough": "Manhattan",
    "neighborhood": "Las Vegas",
    "website": "http://thespotlv.com/",
    "googleMapsUrl": "https://maps.google.com/?cid=4093222192274479935&g_mp=Cidnb29nbGUubWFwcy5wbGFjZXMudjEuUGxhY2VzLlNlYXJjaFRleHQQAhgEIAA",
    "venueTypes": [
      "bar",
      "restaurant"
    ],
    "associatedCountries": [
      "ir-iran"
    ],
    "likelySupporterCountry": "ir-iran",
    "venueIntent": "sports_bar",
    "cuisineTags": [
      "ir iran",
      "ir iran cuisine"
    ],
    "atmosphereTags": [
      "watch-party",
      "loud",
      "big-groups"
    ],
    "showsSoccer": true,
    "openNow": true,
    "priceLevel": 2,
    "rating": 4.5,
    "reviewCount": 459,
    "numberOfScreens": 5,
    "hasProjector": true,
    "hasOutdoorViewing": true,
    "familyFriendly": false,
    "standingRoomFriendly": true,
    "privateEventsAvailable": true,
    "goodForGroups": true,
    "acceptsReservations": true,
    "reservationType": "external_url",
    "reservationUrl": "http://thespotlv.com/",
    "approximateCapacity": 70,
    "capacityBucket": "60_100",
    "capacityConfidence": "estimated",
    "sourceType": "official_api",
    "sourceName": "Google Places",
    "sourceExternalId": "ChIJ--grGcLByIARPxtEpeULzjg",
    "sourceConfidence": 0.92,
    "verificationStatus": "imported",
    "isRealVenue": true,
    "isFeatured": true,
    "isOfficialFanHub": false,
    "gameDayScore": 8.035,
    "fanLikelihoodScore": 8.835,
    "editorialBoost": 0.15,
    "imageUrls": [],
    "createdAt": "2026-04-24T03:10:36.450Z",
    "updatedAt": "2026-04-24T03:10:36.450Z"
  },
  {
    "id": "las-vegas-ir-iran-old-vegas-lounge",
    "slug": "las-vegas-ir-iran-old-vegas-lounge",
    "name": "Old Vegas Lounge",
    "description": "Old Vegas Lounge in Las Vegas for IR Iran.",
    "address": "4130 S Sandhill Rd Suite A-1, Las Vegas, NV 89121, USA",
    "city": "Las Vegas",
    "state": "NV",
    "postalCode": "89121",
    "lat": 36.114923499999996,
    "lng": -115.0910496,
    "borough": "Manhattan",
    "neighborhood": "Las Vegas",
    "website": "https://www.oldvegaslounge.com/",
    "googleMapsUrl": "https://maps.google.com/?cid=17531193481217846527&g_mp=Cidnb29nbGUubWFwcy5wbGFjZXMudjEuUGxhY2VzLlNlYXJjaFRleHQQAhgEIAA",
    "venueTypes": [
      "bar",
      "restaurant"
    ],
    "associatedCountries": [
      "ir-iran"
    ],
    "likelySupporterCountry": "ir-iran",
    "venueIntent": "sports_bar",
    "cuisineTags": [
      "ir iran",
      "ir iran cuisine"
    ],
    "atmosphereTags": [
      "watch-party",
      "loud",
      "big-groups"
    ],
    "showsSoccer": true,
    "openNow": true,
    "priceLevel": 2,
    "rating": 4.9,
    "reviewCount": 62,
    "numberOfScreens": 5,
    "hasProjector": true,
    "hasOutdoorViewing": true,
    "familyFriendly": false,
    "standingRoomFriendly": true,
    "privateEventsAvailable": true,
    "goodForGroups": true,
    "acceptsReservations": true,
    "reservationType": "external_url",
    "reservationUrl": "https://www.oldvegaslounge.com/",
    "approximateCapacity": 70,
    "capacityBucket": "60_100",
    "capacityConfidence": "estimated",
    "sourceType": "official_api",
    "sourceName": "Google Places",
    "sourceExternalId": "ChIJ_-mygfDbyIAR_yyiQJZPS_M",
    "sourceConfidence": 0.92,
    "verificationStatus": "imported",
    "isRealVenue": true,
    "isFeatured": false,
    "isOfficialFanHub": false,
    "gameDayScore": 7.243,
    "fanLikelihoodScore": 8.043000000000001,
    "editorialBoost": 0.15,
    "imageUrls": [],
    "createdAt": "2026-04-24T03:10:36.450Z",
    "updatedAt": "2026-04-24T03:10:36.450Z"
  }
]