[
  {
    "id": "los-angeles-brazil-m-grill-brazilian-churrascaria",
    "slug": "los-angeles-brazil-m-grill-brazilian-churrascaria",
    "name": "M Grill Brazilian Churrascaria",
    "description": "M Grill Brazilian Churrascaria is a watch-party style venue in Los Angeles.",
    "address": "3832 Wilshire Blvd suite 202 suite 202, Los Angeles, CA 90010, USA",
    "city": "los-angeles",
    "state": "CA",
    "postalCode": "90010",
    "lat": 34.061349,
    "lng": -118.31045300000001,
    "borough": "Manhattan",
    "neighborhood": "Los Angeles",
    "website": "https://m-grill.com/",
    "googleMapsUrl": "https://maps.google.com/?cid=6519867953098920635&g_mp=Cidnb29nbGUubWFwcy5wbGFjZXMudjEuUGxhY2VzLlNlYXJjaFRleHQQAhgEIAA",
    "venueTypes": [
      "bar",
      "restaurant"
    ],
    "associatedCountries": [
      "brazil"
    ],
    "likelySupporterCountry": "brazil",
    "venueIntent": "cultural_bar",
    "cuisineTags": [
      "brazil",
      "brazil cuisine"
    ],
    "atmosphereTags": [
      "watch-party",
      "loud",
      "big-groups"
    ],
    "showsSoccer": true,
    "openNow": false,
    "priceLevel": 2,
    "rating": 4.5,
    "reviewCount": 1591,
    "numberOfScreens": 8,
    "hasProjector": true,
    "hasOutdoorViewing": true,
    "familyFriendly": false,
    "standingRoomFriendly": true,
    "privateEventsAvailable": true,
    "goodForGroups": true,
    "acceptsReservations": true,
    "reservationType": "external_url",
    "reservationUrl": "https://m-grill.com/",
    "approximateCapacity": 70,
    "capacityBucket": "60_100",
    "capacityConfidence": "estimated",
    "sourceType": "official_api",
    "sourceName": "Google Places",
    "sourceExternalId": "ChIJC4u0UoW4woARuxLqDlw5e1o",
    "sourceConfidence": 0.92,
    "verificationStatus": "imported",
    "isRealVenue": true,
    "isFeatured": true,
    "isOfficialFanHub": true,
    "gameDayScore": 8.235,
    "fanLikelihoodScore": 9.035,
    "editorialBoost": 0.15,
    "editorialNotes": "Imported from Google Places with name match: brazilian.",
    "supporterNotes": "Country assignment verified via name match.",
    "imageUrls": [],
    "createdAt": "2026-04-25T05:32:25.714Z",
    "updatedAt": "2026-04-25T05:49:06.978Z"
  },
  {
    "id": "los-angeles-brazil-w-brazilian-steakhouse",
    "slug": "los-angeles-brazil-w-brazilian-steakhouse",
    "name": "W Brazilian Steakhouse",
    "description": "W Brazilian Steakhouse is a Brazil restaurant in Los Angeles.",
    "address": "3444 Wilshire Blvd, Los Angeles, CA 90010, USA",
    "city": "los-angeles",
    "state": "CA",
    "postalCode": "90010",
    "lat": 34.0614805,
    "lng": -118.2993628,
    "borough": "Manhattan",
    "neighborhood": "Los Angeles",
    "website": "http://wsteak.net/",
    "googleMapsUrl": "https://maps.google.com/?cid=909179948692122566&g_mp=Cidnb29nbGUubWFwcy5wbGFjZXMudjEuUGxhY2VzLlNlYXJjaFRleHQQAhgEIAA",
    "venueTypes": [
      "restaurant"
    ],
    "associatedCountries": [
      "brazil"
    ],
    "likelySupporterCountry": "brazil",
    "venueIntent": "cultural_restaurant",
    "cuisineTags": [
      "brazil",
      "brazil cuisine"
    ],
    "atmosphereTags": [
      "casual",
      "authentic-food"
    ],
    "showsSoccer": false,
    "openNow": false,
    "priceLevel": 3,
    "rating": 4.5,
    "reviewCount": 215,
    "numberOfScreens": 1,
    "hasProjector": false,
    "hasOutdoorViewing": false,
    "familyFriendly": true,
    "standingRoomFriendly": false,
    "privateEventsAvailable": true,
    "goodForGroups": false,
    "acceptsReservations": true,
    "reservationType": "external_url",
    "reservationUrl": "http://wsteak.net/",
    "approximateCapacity": 45,
    "capacityBucket": "30_60",
    "capacityConfidence": "estimated",
    "sourceType": "official_api",
    "sourceName": "Google Places",
    "sourceExternalId": "ChIJ4xacB1S5woARxquzplgOngw",
    "sourceConfidence": 0.92,
    "verificationStatus": "imported",
    "isRealVenue": true,
    "isFeatured": false,
    "isOfficialFanHub": false,
    "gameDayScore": 6.245000000000001,
    "fanLikelihoodScore": 7.045000000000001,
    "editorialBoost": 0.15,
    "editorialNotes": "Imported from Google Places with name match: brazilian.",
    "supporterNotes": "Country assignment verified via name match.",
    "imageUrls": [],
    "createdAt": "2026-04-25T05:32:25.714Z",
    "updatedAt": "2026-04-25T05:49:06.978Z"
  },
  {
    "id": "los-angeles-brazil-bossa-nova-brazilian-cuisine",
    "slug": "los-angeles-brazil-bossa-nova-brazilian-cuisine",
    "name": "Bossa Nova Brazilian Cuisine",
    "description": "Bossa Nova Brazilian Cuisine is a Brazil bar in Los Angeles.",
    "address": "321 W Olympic Blvd Suite B, Los Angeles, CA 90015, USA",
    "city": "los-angeles",
    "state": "CA",
    "postalCode": "90015",
    "lat": 34.0423792,
    "lng": -118.25925339999999,
    "borough": "Manhattan",
    "neighborhood": "Los Angeles",
    "website": "https://www.bossafood.com/",
    "googleMapsUrl": "https://maps.google.com/?cid=2813204527622150557&g_mp=Cidnb29nbGUubWFwcy5wbGFjZXMudjEuUGxhY2VzLlNlYXJjaFRleHQQAhgEIAA",
    "venueTypes": [
      "bar",
      "restaurant",
      "bakery"
    ],
    "associatedCountries": [
      "brazil"
    ],
    "likelySupporterCountry": "brazil",
    "venueIntent": "cultural_bar",
    "cuisineTags": [
      "brazil",
      "brazil cuisine"
    ],
    "atmosphereTags": [
      "authentic-food",
      "casual",
      "watch-party"
    ],
    "showsSoccer": true,
    "openNow": true,
    "priceLevel": 2,
    "rating": 4.3,
    "reviewCount": 705,
    "numberOfScreens": 3,
    "hasProjector": false,
    "hasOutdoorViewing": true,
    "familyFriendly": true,
    "standingRoomFriendly": true,
    "privateEventsAvailable": true,
    "goodForGroups": true,
    "acceptsReservations": true,
    "reservationType": "external_url",
    "reservationUrl": "https://www.bossafood.com/",
    "approximateCapacity": 70,
    "capacityBucket": "60_100",
    "capacityConfidence": "estimated",
    "sourceType": "official_api",
    "sourceName": "Google Places",
    "sourceExternalId": "ChIJp3y0Q-XHwoARnVlw5ZyCCic",
    "sourceConfidence": 0.92,
    "verificationStatus": "imported",
    "isRealVenue": true,
    "isFeatured": false,
    "isOfficialFanHub": false,
    "gameDayScore": 7.305,
    "fanLikelihoodScore": 8.105,
    "editorialBoost": 0.15,
    "editorialNotes": "Imported from Google Places with name match: brazilian.",
    "supporterNotes": "Country assignment verified via name match.",
    "imageUrls": [],
    "createdAt": "2026-04-25T05:32:25.714Z",
    "updatedAt": "2026-04-25T05:49:06.978Z"
  },
  {
    "id": "los-angeles-brazil-fogo-de-ch-o-brazilian-steakhouse",
    "slug": "los-angeles-brazil-fogo-de-ch-o-brazilian-steakhouse",
    "name": "Fogo de Chão Brazilian Steakhouse",
    "description": "Fogo de Chão Brazilian Steakhouse is a Brazil restaurant in Los Angeles.",
    "address": "800 S Figueroa St, Los Angeles, CA 90017, USA",
    "city": "los-angeles",
    "state": "CA",
    "postalCode": "90017",
    "lat": 34.0476186,
    "lng": -118.26108760000001,
    "borough": "Manhattan",
    "neighborhood": "Los Angeles",
    "website": "https://fogodechao.com/location/los-angeles/",
    "googleMapsUrl": "https://maps.google.com/?cid=11718307920278446761&g_mp=Cidnb29nbGUubWFwcy5wbGFjZXMudjEuUGxhY2VzLlNlYXJjaFRleHQQAhgEIAA",
    "venueTypes": [
      "restaurant"
    ],
    "associatedCountries": [
      "brazil"
    ],
    "likelySupporterCountry": "brazil",
    "venueIntent": "cultural_restaurant",
    "cuisineTags": [
      "brazil",
      "brazil cuisine"
    ],
    "atmosphereTags": [
      "casual",
      "authentic-food"
    ],
    "showsSoccer": false,
    "openNow": false,
    "priceLevel": 3,
    "rating": 4.6,
    "reviewCount": 5408,
    "numberOfScreens": 1,
    "hasProjector": false,
    "hasOutdoorViewing": false,
    "familyFriendly": true,
    "standingRoomFriendly": false,
    "privateEventsAvailable": true,
    "goodForGroups": false,
    "acceptsReservations": true,
    "reservationType": "external_url",
    "reservationUrl": "https://fogodechao.com/location/los-angeles/",
    "approximateCapacity": 45,
    "capacityBucket": "30_60",
    "capacityConfidence": "estimated",
    "sourceType": "official_api",
    "sourceName": "Google Places",
    "sourceExternalId": "ChIJi-KL2bbHwoARqeLXnPfKn6I",
    "sourceConfidence": 0.92,
    "verificationStatus": "imported",
    "isRealVenue": true,
    "isFeatured": false,
    "isOfficialFanHub": false,
    "gameDayScore": 7,
    "fanLikelihoodScore": 7.8,
    "editorialBoost": 0.15,
    "editorialNotes": "Imported from Google Places with name match: brazilian.",
    "supporterNotes": "Country assignment verified via name match.",
    "imageUrls": [],
    "createdAt": "2026-04-25T05:32:25.714Z",
    "updatedAt": "2026-04-25T05:49:06.978Z"
  },
  {
    "id": "los-angeles-brazil-casa-ipanema",
    "slug": "los-angeles-brazil-casa-ipanema",
    "name": "Casa Ipanema",
    "description": "Casa Ipanema is a Brazil restaurant in Los Angeles.",
    "address": "501 S Olive St, Los Angeles, CA 90013, USA",
    "city": "los-angeles",
    "state": "CA",
    "postalCode": "90013",
    "lat": 34.049396099999996,
    "lng": -118.25310060000001,
    "borough": "Manhattan",
    "neighborhood": "Los Angeles",
    "website": "https://www.casaipanema.com/",
    "googleMapsUrl": "https://maps.google.com/?cid=14363982697733064356&g_mp=Cidnb29nbGUubWFwcy5wbGFjZXMudjEuUGxhY2VzLlNlYXJjaFRleHQQAhgEIAA",
    "venueTypes": [
      "restaurant"
    ],
    "associatedCountries": [
      "brazil"
    ],
    "likelySupporterCountry": "brazil",
    "venueIntent": "cultural_restaurant",
    "cuisineTags": [
      "brazil",
      "brazil cuisine"
    ],
    "atmosphereTags": [
      "casual",
      "authentic-food"
    ],
    "showsSoccer": false,
    "openNow": true,
    "priceLevel": 3,
    "rating": 4.8,
    "reviewCount": 251,
    "numberOfScreens": 1,
    "hasProjector": false,
    "hasOutdoorViewing": false,
    "familyFriendly": true,
    "standingRoomFriendly": false,
    "privateEventsAvailable": true,
    "goodForGroups": false,
    "acceptsReservations": true,
    "reservationType": "external_url",
    "reservationUrl": "https://www.casaipanema.com/",
    "approximateCapacity": 45,
    "capacityBucket": "30_60",
    "capacityConfidence": "estimated",
    "sourceType": "official_api",
    "sourceName": "Google Places",
    "sourceExternalId": "ChIJzxDy_onHwoARpIY88igeV8c",
    "sourceConfidence": 0.92,
    "verificationStatus": "imported",
    "isRealVenue": true,
    "isFeatured": false,
    "isOfficialFanHub": false,
    "gameDayScore": 6.734,
    "fanLikelihoodScore": 7.534,
    "editorialBoost": 0.15,
    "editorialNotes": "Imported from Google Places with name match: ipanema.",
    "supporterNotes": "Country assignment verified via name match.",
    "imageUrls": [],
    "createdAt": "2026-04-25T05:32:25.714Z",
    "updatedAt": "2026-04-25T05:49:06.978Z"
  },
  {
    "id": "los-angeles-brazil-green-field-churrascaria",
    "slug": "los-angeles-brazil-green-field-churrascaria",
    "name": "Green Field Churrascaria",
    "description": "Green Field Churrascaria is a Brazil restaurant in Los Angeles.",
    "address": "5305 Pacific Coast Hwy, Long Beach, CA 90804, USA",
    "city": "los-angeles",
    "state": "CA",
    "postalCode": "90804",
    "lat": 33.7817256,
    "lng": -118.13088289999999,
    "borough": "Manhattan",
    "neighborhood": "Los Angeles",
    "website": "http://www.greenfieldchurrascaria.com/",
    "googleMapsUrl": "https://maps.google.com/?cid=17535806981330580584&g_mp=Cidnb29nbGUubWFwcy5wbGFjZXMudjEuUGxhY2VzLlNlYXJjaFRleHQQAhgEIAA",
    "venueTypes": [
      "restaurant"
    ],
    "associatedCountries": [
      "brazil"
    ],
    "likelySupporterCountry": "brazil",
    "venueIntent": "cultural_restaurant",
    "cuisineTags": [
      "brazil",
      "brazil cuisine"
    ],
    "atmosphereTags": [
      "casual",
      "authentic-food"
    ],
    "showsSoccer": false,
    "openNow": true,
    "priceLevel": 3,
    "rating": 4.5,
    "reviewCount": 2038,
    "numberOfScreens": 1,
    "hasProjector": false,
    "hasOutdoorViewing": false,
    "familyFriendly": true,
    "standingRoomFriendly": false,
    "privateEventsAvailable": true,
    "goodForGroups": false,
    "acceptsReservations": true,
    "reservationType": "external_url",
    "reservationUrl": "http://www.greenfieldchurrascaria.com/",
    "approximateCapacity": 45,
    "capacityBucket": "30_60",
    "capacityConfidence": "estimated",
    "sourceType": "official_api",
    "sourceName": "Google Places",
    "sourceExternalId": "ChIJKayXosYx3YARaDQGdIqzW_M",
    "sourceConfidence": 0.92,
    "verificationStatus": "imported",
    "isRealVenue": true,
    "isFeatured": false,
    "isOfficialFanHub": false,
    "gameDayScore": 6.885000000000001,
    "fanLikelihoodScore": 7.6850000000000005,
    "editorialBoost": 0.15,
    "editorialNotes": "Imported from Google Places with name match: churrascaria.",
    "supporterNotes": "Country assignment verified via name match.",
    "imageUrls": [],
    "createdAt": "2026-04-25T05:32:25.714Z",
    "updatedAt": "2026-04-25T05:49:06.978Z"
  },
  {
    "id": "los-angeles-brazil-h-h-brazilian-steakhouse",
    "slug": "los-angeles-brazil-h-h-brazilian-steakhouse",
    "name": "H&H Brazilian Steakhouse",
    "description": "H&H Brazilian Steakhouse is a Brazil restaurant in Los Angeles.",
    "address": "518 W 7th St, Los Angeles, CA 90014, USA",
    "city": "los-angeles",
    "state": "CA",
    "postalCode": "90014",
    "lat": 34.0468498,
    "lng": -118.25617410000001,
    "borough": "Manhattan",
    "neighborhood": "Los Angeles",
    "website": "http://www.hhsteakhouse.com/",
    "googleMapsUrl": "https://maps.google.com/?cid=16347238952334872392&g_mp=Cidnb29nbGUubWFwcy5wbGFjZXMudjEuUGxhY2VzLlNlYXJjaFRleHQQAhgEIAA",
    "venueTypes": [
      "restaurant"
    ],
    "associatedCountries": [
      "brazil"
    ],
    "likelySupporterCountry": "brazil",
    "venueIntent": "cultural_restaurant",
    "cuisineTags": [
      "brazil",
      "brazil cuisine"
    ],
    "atmosphereTags": [
      "casual",
      "authentic-food"
    ],
    "showsSoccer": false,
    "openNow": false,
    "priceLevel": 3,
    "rating": 4.7,
    "reviewCount": 1860,
    "numberOfScreens": 1,
    "hasProjector": false,
    "hasOutdoorViewing": false,
    "familyFriendly": true,
    "standingRoomFriendly": false,
    "privateEventsAvailable": true,
    "goodForGroups": false,
    "acceptsReservations": true,
    "reservationType": "external_url",
    "reservationUrl": "http://www.hhsteakhouse.com/",
    "approximateCapacity": 45,
    "capacityBucket": "30_60",
    "capacityConfidence": "estimated",
    "sourceType": "official_api",
    "sourceName": "Google Places",
    "sourceExternalId": "ChIJuVics2PHwoARSE9ZPDcP3eI",
    "sourceConfidence": 0.92,
    "verificationStatus": "imported",
    "isRealVenue": true,
    "isFeatured": false,
    "isOfficialFanHub": false,
    "gameDayScore": 7.115,
    "fanLikelihoodScore": 7.915,
    "editorialBoost": 0.15,
    "editorialNotes": "Imported from Google Places with name match: brazilian.",
    "supporterNotes": "Country assignment verified via name match.",
    "imageUrls": [],
    "createdAt": "2026-04-25T05:32:25.714Z",
    "updatedAt": "2026-04-25T05:49:06.978Z"
  },
  {
    "id": "los-angeles-brazil-fogo-de-ch-o-brazilian-steakhouse",
    "slug": "los-angeles-brazil-fogo-de-ch-o-brazilian-steakhouse",
    "name": "Fogo de Chão Brazilian Steakhouse",
    "description": "Fogo de Chão Brazilian Steakhouse is a Brazil restaurant in Los Angeles.",
    "address": "2121 Rosecrans Ave Ste 1399, El Segundo, CA 90245, USA",
    "city": "los-angeles",
    "state": "CA",
    "postalCode": "90245",
    "lat": 33.9022978,
    "lng": -118.3873758,
    "borough": "Manhattan",
    "neighborhood": "Los Angeles",
    "website": "https://fogodechao.com/location/el-segundo/",
    "googleMapsUrl": "https://maps.google.com/?cid=777360446409787801&g_mp=Cidnb29nbGUubWFwcy5wbGFjZXMudjEuUGxhY2VzLlNlYXJjaFRleHQQAhgEIAA",
    "venueTypes": [
      "restaurant"
    ],
    "associatedCountries": [
      "brazil"
    ],
    "likelySupporterCountry": "brazil",
    "venueIntent": "cultural_restaurant",
    "cuisineTags": [
      "brazil",
      "brazil cuisine"
    ],
    "atmosphereTags": [
      "casual",
      "authentic-food"
    ],
    "showsSoccer": false,
    "openNow": false,
    "priceLevel": 3,
    "rating": 4.7,
    "reviewCount": 4579,
    "numberOfScreens": 1,
    "hasProjector": false,
    "hasOutdoorViewing": false,
    "familyFriendly": true,
    "standingRoomFriendly": false,
    "privateEventsAvailable": true,
    "goodForGroups": false,
    "acceptsReservations": true,
    "reservationType": "external_url",
    "reservationUrl": "https://fogodechao.com/location/el-segundo/",
    "approximateCapacity": 45,
    "capacityBucket": "30_60",
    "capacityConfidence": "estimated",
    "sourceType": "official_api",
    "sourceName": "Google Places",
    "sourceExternalId": "ChIJn4CnfIK1woARmcmxFjW9yQo",
    "sourceConfidence": 0.92,
    "verificationStatus": "imported",
    "isRealVenue": true,
    "isFeatured": false,
    "isOfficialFanHub": false,
    "gameDayScore": 7.115,
    "fanLikelihoodScore": 7.915,
    "editorialBoost": 0.15,
    "editorialNotes": "Imported from Google Places with name match: brazilian.",
    "supporterNotes": "Country assignment verified via name match.",
    "imageUrls": [],
    "createdAt": "2026-04-25T05:32:25.714Z",
    "updatedAt": "2026-04-25T05:49:06.978Z"
  },
  {
    "id": "los-angeles-brazil-h-h-brazilian-steakhouse",
    "slug": "los-angeles-brazil-h-h-brazilian-steakhouse",
    "name": "H&H Brazilian Steakhouse",
    "description": "H&H Brazilian Steakhouse is a Brazil restaurant in Los Angeles.",
    "address": "8500 Beverly Blvd #113, Los Angeles, CA 90048, USA",
    "city": "los-angeles",
    "state": "CA",
    "postalCode": "90048",
    "lat": 34.0737021,
    "lng": -118.3767578,
    "borough": "Manhattan",
    "neighborhood": "Los Angeles",
    "website": "http://www.hhsteakhouse.com/",
    "googleMapsUrl": "https://maps.google.com/?cid=1413306122886010611&g_mp=Cidnb29nbGUubWFwcy5wbGFjZXMudjEuUGxhY2VzLlNlYXJjaFRleHQQAhgEIAA",
    "venueTypes": [
      "restaurant"
    ],
    "associatedCountries": [
      "brazil"
    ],
    "likelySupporterCountry": "brazil",
    "venueIntent": "cultural_restaurant",
    "cuisineTags": [
      "brazil",
      "brazil cuisine"
    ],
    "atmosphereTags": [
      "casual",
      "authentic-food"
    ],
    "showsSoccer": false,
    "openNow": false,
    "priceLevel": 3,
    "rating": 4.8,
    "reviewCount": 1839,
    "numberOfScreens": 1,
    "hasProjector": false,
    "hasOutdoorViewing": false,
    "familyFriendly": true,
    "standingRoomFriendly": false,
    "privateEventsAvailable": true,
    "goodForGroups": false,
    "acceptsReservations": true,
    "reservationType": "external_url",
    "reservationUrl": "http://www.hhsteakhouse.com/",
    "approximateCapacity": 45,
    "capacityBucket": "30_60",
    "capacityConfidence": "estimated",
    "sourceType": "official_api",
    "sourceName": "Google Places",
    "sourceExternalId": "ChIJkXw0B6G5woAR81aBRW4SnRM",
    "sourceConfidence": 0.92,
    "verificationStatus": "imported",
    "isRealVenue": true,
    "isFeatured": false,
    "isOfficialFanHub": false,
    "gameDayScore": 7.23,
    "fanLikelihoodScore": 8.030000000000001,
    "editorialBoost": 0.15,
    "editorialNotes": "Imported from Google Places with name match: brazilian.",
    "supporterNotes": "Country assignment verified via name match.",
    "imageUrls": [],
    "createdAt": "2026-04-25T05:32:25.714Z",
    "updatedAt": "2026-04-25T05:49:06.978Z"
  },
  {
    "id": "los-angeles-brazil-bossa-nova-brazilian-cuisine",
    "slug": "los-angeles-brazil-bossa-nova-brazilian-cuisine",
    "name": "Bossa Nova Brazilian Cuisine",
    "description": "Bossa Nova Brazilian Cuisine is a Brazil bar in Los Angeles.",
    "address": "7181 Sunset Blvd, Los Angeles, CA 90046, USA",
    "city": "los-angeles",
    "state": "CA",
    "postalCode": "90046",
    "lat": 34.0982382,
    "lng": -118.34658100000001,
    "borough": "Manhattan",
    "neighborhood": "Los Angeles",
    "website": "https://www.bossafood.com/",
    "googleMapsUrl": "https://maps.google.com/?cid=9046002365038093881&g_mp=Cidnb29nbGUubWFwcy5wbGFjZXMudjEuUGxhY2VzLlNlYXJjaFRleHQQAhgEIAA",
    "venueTypes": [
      "bar",
      "restaurant",
      "bakery"
    ],
    "associatedCountries": [
      "brazil"
    ],
    "likelySupporterCountry": "brazil",
    "venueIntent": "cultural_bar",
    "cuisineTags": [
      "brazil",
      "brazil cuisine"
    ],
    "atmosphereTags": [
      "authentic-food",
      "casual",
      "watch-party"
    ],
    "showsSoccer": true,
    "openNow": true,
    "priceLevel": 2,
    "rating": 4.4,
    "reviewCount": 3632,
    "numberOfScreens": 3,
    "hasProjector": false,
    "hasOutdoorViewing": true,
    "familyFriendly": true,
    "standingRoomFriendly": true,
    "privateEventsAvailable": true,
    "goodForGroups": true,
    "acceptsReservations": true,
    "reservationType": "external_url",
    "reservationUrl": "https://www.bossafood.com/",
    "approximateCapacity": 70,
    "capacityBucket": "60_100",
    "capacityConfidence": "estimated",
    "sourceType": "official_api",
    "sourceName": "Google Places",
    "sourceExternalId": "ChIJJ0YDr9i-woAROWZwJTnbiX0",
    "sourceConfidence": 0.92,
    "verificationStatus": "imported",
    "isRealVenue": true,
    "isFeatured": false,
    "isOfficialFanHub": false,
    "gameDayScore": 7.42,
    "fanLikelihoodScore": 8.22,
    "editorialBoost": 0.15,
    "editorialNotes": "Imported from Google Places with name match: brazilian.",
    "supporterNotes": "Country assignment verified via name match.",
    "imageUrls": [],
    "createdAt": "2026-04-25T05:32:25.714Z",
    "updatedAt": "2026-04-25T05:49:06.978Z"
  }
]