[
  {
    "id": "monterrey-saudi-arabia-arabic-food-shawarma-and-falafel-mr-abbas",
    "slug": "monterrey-saudi-arabia-arabic-food-shawarma-and-falafel-mr-abbas",
    "name": "Arabic food. Shawarma and Falafel Mr. Abbas",
    "description": "Arabic food. Shawarma and Falafel Mr. Abbas is a Saudi Arabia restaurant in Monterrey.",
    "address": "64000, José Garibaldi 477, Centro, 64000 Monterrey, N.L., Mexico",
    "city": "monterrey",
    "state": "NL",
    "postalCode": "64000",
    "lat": 25.672958899999998,
    "lng": -100.3168357,
    "borough": "Manhattan",
    "neighborhood": "Monterrey",
    "googleMapsUrl": "https://maps.google.com/?cid=11585086755158816605&g_mp=Cidnb29nbGUubWFwcy5wbGFjZXMudjEuUGxhY2VzLlNlYXJjaFRleHQQAhgEIAA",
    "venueTypes": [
      "restaurant"
    ],
    "associatedCountries": [
      "saudi-arabia"
    ],
    "likelySupporterCountry": "saudi-arabia",
    "venueIntent": "cultural_restaurant",
    "cuisineTags": [
      "saudi arabia",
      "saudi arabia cuisine"
    ],
    "atmosphereTags": [
      "casual",
      "authentic-food"
    ],
    "showsSoccer": false,
    "openNow": false,
    "priceLevel": 3,
    "rating": 4.6,
    "reviewCount": 345,
    "numberOfScreens": 1,
    "hasProjector": false,
    "hasOutdoorViewing": false,
    "familyFriendly": true,
    "standingRoomFriendly": false,
    "privateEventsAvailable": false,
    "goodForGroups": false,
    "acceptsReservations": false,
    "reservationType": "none",
    "approximateCapacity": 45,
    "capacityBucket": "30_60",
    "capacityConfidence": "estimated",
    "sourceType": "official_api",
    "sourceName": "Google Places",
    "sourceExternalId": "ChIJH_s9xCe-YoYRXfdS_QV_xqA",
    "sourceConfidence": 0.92,
    "verificationStatus": "imported",
    "isRealVenue": true,
    "isFeatured": false,
    "isOfficialFanHub": false,
    "gameDayScore": 6.88,
    "fanLikelihoodScore": 7.68,
    "editorialBoost": 0.15,
    "editorialNotes": "Imported from Google Places with name match: arabic.",
    "supporterNotes": "Country assignment verified via name match.",
    "imageUrls": [],
    "createdAt": "2026-04-25T05:40:33.043Z",
    "updatedAt": "2026-04-25T05:49:07.279Z"
  }
]