[
  {
    "id": "san-francisco-spain-destapas-sf",
    "slug": "san-francisco-spain-destapas-sf",
    "name": "Destapas SF",
    "description": "Destapas SF is a Spain bar in San Francisco.",
    "address": "2708 24th St, San Francisco, CA 94110, USA",
    "city": "san-francisco",
    "state": "CA",
    "postalCode": "94110",
    "lat": 37.7531052,
    "lng": -122.40686289999998,
    "borough": "Manhattan",
    "neighborhood": "San Francisco",
    "website": "http://destapas.com/",
    "googleMapsUrl": "https://maps.google.com/?cid=2641340210319183662&g_mp=Cidnb29nbGUubWFwcy5wbGFjZXMudjEuUGxhY2VzLlNlYXJjaFRleHQQAhgEIAA",
    "venueTypes": [
      "bar",
      "restaurant"
    ],
    "associatedCountries": [],
    "likelySupporterCountry": null,
    "venueIntent": "bar_with_tv",
    "cuisineTags": [
      "spain",
      "spain cuisine"
    ],
    "atmosphereTags": [
      "authentic-food",
      "casual",
      "watch-party"
    ],
    "showsSoccer": true,
    "openNow": false,
    "priceLevel": 2,
    "rating": 4.7,
    "reviewCount": 439,
    "numberOfScreens": 3,
    "hasProjector": false,
    "hasOutdoorViewing": true,
    "familyFriendly": false,
    "standingRoomFriendly": true,
    "privateEventsAvailable": true,
    "goodForGroups": true,
    "acceptsReservations": true,
    "reservationType": "external_url",
    "reservationUrl": "http://destapas.com/",
    "approximateCapacity": 70,
    "capacityBucket": "60_100",
    "capacityConfidence": "estimated",
    "sourceType": "official_api",
    "sourceName": "Google Places",
    "sourceExternalId": "ChIJ_SU7FSB_j4ARLs8HR-3spyQ",
    "sourceConfidence": 0.92,
    "verificationStatus": "imported",
    "isRealVenue": true,
    "isFeatured": false,
    "isOfficialFanHub": false,
    "gameDayScore": 7.765,
    "fanLikelihoodScore": 8.565,
    "editorialBoost": 0.15,
    "editorialNotes": "Imported from Google Places with type match: spanish_restaurant.",
    "supporterNotes": "Country assignment verified via type match.",
    "imageUrls": [],
    "createdAt": "2026-04-25T05:33:53.156Z",
    "updatedAt": "2026-04-25T05:49:07.421Z"
  },
  {
    "id": "san-francisco-spain-picaro",
    "slug": "san-francisco-spain-picaro",
    "name": "Picaro",
    "description": "Picaro is a Spain bar in San Francisco.",
    "address": "3120 16th St, San Francisco, CA 94103, USA",
    "city": "san-francisco",
    "state": "CA",
    "postalCode": "94103",
    "lat": 37.7650784,
    "lng": -122.42252219999999,
    "borough": "Manhattan",
    "neighborhood": "San Francisco",
    "website": "http://www.picarocafe.com/",
    "googleMapsUrl": "https://maps.google.com/?cid=4116125142723223573&g_mp=Cidnb29nbGUubWFwcy5wbGFjZXMudjEuUGxhY2VzLlNlYXJjaFRleHQQAhgEIAA",
    "venueTypes": [
      "bar",
      "restaurant"
    ],
    "associatedCountries": [],
    "likelySupporterCountry": null,
    "venueIntent": "bar_with_tv",
    "cuisineTags": [
      "spain",
      "spain cuisine"
    ],
    "atmosphereTags": [
      "authentic-food",
      "casual",
      "watch-party"
    ],
    "showsSoccer": true,
    "openNow": false,
    "priceLevel": 2,
    "rating": 4.5,
    "reviewCount": 1590,
    "numberOfScreens": 3,
    "hasProjector": false,
    "hasOutdoorViewing": true,
    "familyFriendly": false,
    "standingRoomFriendly": true,
    "privateEventsAvailable": true,
    "goodForGroups": true,
    "acceptsReservations": true,
    "reservationType": "external_url",
    "reservationUrl": "http://www.picarocafe.com/",
    "approximateCapacity": 70,
    "capacityBucket": "60_100",
    "capacityConfidence": "estimated",
    "sourceType": "official_api",
    "sourceName": "Google Places",
    "sourceExternalId": "ChIJv117QSJ-j4ARFWASVwJqHzk",
    "sourceConfidence": 0.92,
    "verificationStatus": "imported",
    "isRealVenue": true,
    "isFeatured": false,
    "isOfficialFanHub": false,
    "gameDayScore": 7.535,
    "fanLikelihoodScore": 8.335,
    "editorialBoost": 0.15,
    "editorialNotes": "Imported from Google Places with type match: spanish_restaurant.",
    "supporterNotes": "Country assignment verified via type match.",
    "imageUrls": [],
    "createdAt": "2026-04-25T05:33:53.157Z",
    "updatedAt": "2026-04-25T05:49:07.422Z"
  },
  {
    "id": "san-francisco-spain-coqueta",
    "slug": "san-francisco-spain-coqueta",
    "name": "Coqueta",
    "description": "Coqueta is a Spain bar in San Francisco.",
    "address": "Pier 5 The Embarcadero, San Francisco, CA 94111, USA",
    "city": "san-francisco",
    "state": "CA",
    "postalCode": "94111",
    "lat": 37.7985824,
    "lng": -122.3966387,
    "borough": "Manhattan",
    "neighborhood": "San Francisco",
    "website": "https://www.coquetasf.com/",
    "googleMapsUrl": "https://maps.google.com/?cid=18211740569183750920&g_mp=Cidnb29nbGUubWFwcy5wbGFjZXMudjEuUGxhY2VzLlNlYXJjaFRleHQQAhgEIAA",
    "venueTypes": [
      "bar",
      "restaurant"
    ],
    "associatedCountries": [],
    "likelySupporterCountry": null,
    "venueIntent": "bar_with_tv",
    "cuisineTags": [
      "spain",
      "spain cuisine"
    ],
    "atmosphereTags": [
      "authentic-food",
      "casual",
      "watch-party"
    ],
    "showsSoccer": true,
    "openNow": false,
    "priceLevel": 2,
    "rating": 4.4,
    "reviewCount": 2804,
    "numberOfScreens": 3,
    "hasProjector": false,
    "hasOutdoorViewing": true,
    "familyFriendly": false,
    "standingRoomFriendly": true,
    "privateEventsAvailable": true,
    "goodForGroups": true,
    "acceptsReservations": true,
    "reservationType": "external_url",
    "reservationUrl": "https://www.coquetasf.com/",
    "approximateCapacity": 70,
    "capacityBucket": "60_100",
    "capacityConfidence": "estimated",
    "sourceType": "official_api",
    "sourceName": "Google Places",
    "sourceExternalId": "ChIJA8_SN2eAhYARCIvEx44Zvfw",
    "sourceConfidence": 0.92,
    "verificationStatus": "imported",
    "isRealVenue": true,
    "isFeatured": false,
    "isOfficialFanHub": false,
    "gameDayScore": 7.42,
    "fanLikelihoodScore": 8.22,
    "editorialBoost": 0.15,
    "editorialNotes": "Imported from Google Places with type match: spanish_restaurant.",
    "supporterNotes": "Country assignment verified via type match.",
    "imageUrls": [],
    "createdAt": "2026-04-25T05:33:53.157Z",
    "updatedAt": "2026-04-25T05:49:07.422Z"
  },
  {
    "id": "san-francisco-spain-canela-bistro-bar",
    "slug": "san-francisco-spain-canela-bistro-bar",
    "name": "Canela Bistro Bar",
    "description": "Canela Bistro Bar is a Spain bar in San Francisco.",
    "address": "2272 Market St, San Francisco, CA 94114, USA",
    "city": "san-francisco",
    "state": "CA",
    "postalCode": "94114",
    "lat": 37.764962000000004,
    "lng": -122.43258270000001,
    "borough": "Manhattan",
    "neighborhood": "San Francisco",
    "website": "https://canelasf.com/",
    "googleMapsUrl": "https://maps.google.com/?cid=16266874511284882601&g_mp=Cidnb29nbGUubWFwcy5wbGFjZXMudjEuUGxhY2VzLlNlYXJjaFRleHQQAhgEIAA",
    "venueTypes": [
      "bar",
      "restaurant"
    ],
    "associatedCountries": [],
    "likelySupporterCountry": null,
    "venueIntent": "bar_with_tv",
    "cuisineTags": [
      "spain",
      "spain cuisine"
    ],
    "atmosphereTags": [
      "authentic-food",
      "casual",
      "watch-party"
    ],
    "showsSoccer": true,
    "openNow": false,
    "priceLevel": 2,
    "rating": 4.6,
    "reviewCount": 580,
    "numberOfScreens": 3,
    "hasProjector": false,
    "hasOutdoorViewing": true,
    "familyFriendly": false,
    "standingRoomFriendly": true,
    "privateEventsAvailable": true,
    "goodForGroups": true,
    "acceptsReservations": true,
    "reservationType": "external_url",
    "reservationUrl": "https://canelasf.com/",
    "approximateCapacity": 70,
    "capacityBucket": "60_100",
    "capacityConfidence": "estimated",
    "sourceType": "official_api",
    "sourceName": "Google Places",
    "sourceExternalId": "ChIJh8PT9xx-j4ARqcz9si6Mv-E",
    "sourceConfidence": 0.92,
    "verificationStatus": "imported",
    "isRealVenue": true,
    "isFeatured": false,
    "isOfficialFanHub": false,
    "gameDayScore": 7.6499999999999995,
    "fanLikelihoodScore": 8.45,
    "editorialBoost": 0.15,
    "editorialNotes": "Imported from Google Places with type match: spanish_restaurant.",
    "supporterNotes": "Country assignment verified via type match.",
    "imageUrls": [],
    "createdAt": "2026-04-25T05:33:53.157Z",
    "updatedAt": "2026-04-25T05:49:07.422Z"
  },
  {
    "id": "san-francisco-spain-esperpento-restaurant",
    "slug": "san-francisco-spain-esperpento-restaurant",
    "name": "Esperpento Restaurant",
    "description": "Esperpento Restaurant is a Spain bar in San Francisco.",
    "address": "3295 22nd St, San Francisco, CA 94110, USA",
    "city": "san-francisco",
    "state": "CA",
    "postalCode": "94110",
    "lat": 37.7551671,
    "lng": -122.420679,
    "borough": "Manhattan",
    "neighborhood": "San Francisco",
    "website": "http://esperpentosf.com/",
    "googleMapsUrl": "https://maps.google.com/?cid=2346688676068849161&g_mp=Cidnb29nbGUubWFwcy5wbGFjZXMudjEuUGxhY2VzLlNlYXJjaFRleHQQAhgEIAA",
    "venueTypes": [
      "bar",
      "restaurant"
    ],
    "associatedCountries": [],
    "likelySupporterCountry": null,
    "venueIntent": "bar_with_tv",
    "cuisineTags": [
      "spain",
      "spain cuisine"
    ],
    "atmosphereTags": [
      "authentic-food",
      "casual",
      "watch-party"
    ],
    "showsSoccer": true,
    "openNow": false,
    "priceLevel": 2,
    "rating": 4.4,
    "reviewCount": 876,
    "numberOfScreens": 3,
    "hasProjector": false,
    "hasOutdoorViewing": true,
    "familyFriendly": false,
    "standingRoomFriendly": true,
    "privateEventsAvailable": true,
    "goodForGroups": true,
    "acceptsReservations": true,
    "reservationType": "external_url",
    "reservationUrl": "http://esperpentosf.com/",
    "approximateCapacity": 70,
    "capacityBucket": "60_100",
    "capacityConfidence": "estimated",
    "sourceType": "official_api",
    "sourceName": "Google Places",
    "sourceExternalId": "ChIJpQ_u_D5-j4ARCfaD5-ockSA",
    "sourceConfidence": 0.92,
    "verificationStatus": "imported",
    "isRealVenue": true,
    "isFeatured": false,
    "isOfficialFanHub": false,
    "gameDayScore": 7.42,
    "fanLikelihoodScore": 8.22,
    "editorialBoost": 0.15,
    "editorialNotes": "Imported from Google Places with type match: spanish_restaurant.",
    "supporterNotes": "Country assignment verified via type match.",
    "imageUrls": [],
    "createdAt": "2026-04-25T05:33:53.157Z",
    "updatedAt": "2026-04-25T05:49:07.422Z"
  },
  {
    "id": "san-francisco-spain-abrazo",
    "slug": "san-francisco-spain-abrazo",
    "name": "Abrazo",
    "description": "Abrazo is a Spain restaurant in San Francisco.",
    "address": "2000 Hyde St, San Francisco, CA 94109, USA",
    "city": "san-francisco",
    "state": "CA",
    "postalCode": "94109",
    "lat": 37.7993433,
    "lng": -122.41890269999999,
    "borough": "Manhattan",
    "neighborhood": "San Francisco",
    "website": "https://www.abrazosf.com/",
    "googleMapsUrl": "https://maps.google.com/?cid=1160988477517911544&g_mp=Cidnb29nbGUubWFwcy5wbGFjZXMudjEuUGxhY2VzLlNlYXJjaFRleHQQAhgEIAA",
    "venueTypes": [
      "restaurant"
    ],
    "associatedCountries": [],
    "likelySupporterCountry": null,
    "venueIntent": "cultural_restaurant",
    "cuisineTags": [
      "spain",
      "spain cuisine"
    ],
    "atmosphereTags": [
      "casual",
      "authentic-food"
    ],
    "showsSoccer": false,
    "openNow": false,
    "priceLevel": 3,
    "rating": 4.7,
    "reviewCount": 251,
    "numberOfScreens": 1,
    "hasProjector": false,
    "hasOutdoorViewing": false,
    "familyFriendly": true,
    "standingRoomFriendly": false,
    "privateEventsAvailable": true,
    "goodForGroups": false,
    "acceptsReservations": true,
    "reservationType": "external_url",
    "reservationUrl": "https://www.abrazosf.com/",
    "approximateCapacity": 45,
    "capacityBucket": "30_60",
    "capacityConfidence": "estimated",
    "sourceType": "official_api",
    "sourceName": "Google Places",
    "sourceExternalId": "ChIJC2jSzuiAhYAR-NXGft6oHBA",
    "sourceConfidence": 0.92,
    "verificationStatus": "imported",
    "isRealVenue": true,
    "isFeatured": false,
    "isOfficialFanHub": false,
    "gameDayScore": 6.619,
    "fanLikelihoodScore": 7.419,
    "editorialBoost": 0.15,
    "editorialNotes": "Imported from Google Places with type match: spanish_restaurant.",
    "supporterNotes": "Country assignment verified via type match.",
    "imageUrls": [],
    "createdAt": "2026-04-25T05:33:53.157Z",
    "updatedAt": "2026-04-25T05:49:07.422Z"
  },
  {
    "id": "san-francisco-spain-bota-tapas-paella-bar",
    "slug": "san-francisco-spain-bota-tapas-paella-bar",
    "name": "Bota Tapas & Paella Bar",
    "description": "Bota Tapas & Paella Bar is a Spain restaurant in San Francisco.",
    "address": "490 Geary St, San Francisco, CA 94102, USA",
    "city": "san-francisco",
    "state": "CA",
    "postalCode": "94102",
    "lat": 37.7871284,
    "lng": -122.41127680000001,
    "borough": "Manhattan",
    "neighborhood": "San Francisco",
    "website": "http://botasf.com/",
    "googleMapsUrl": "https://maps.google.com/?cid=341264616616735477&g_mp=Cidnb29nbGUubWFwcy5wbGFjZXMudjEuUGxhY2VzLlNlYXJjaFRleHQQAhgEIAA",
    "venueTypes": [
      "restaurant"
    ],
    "associatedCountries": [
      "spain"
    ],
    "likelySupporterCountry": "spain",
    "venueIntent": "cultural_restaurant",
    "cuisineTags": [
      "spain",
      "spain cuisine"
    ],
    "atmosphereTags": [
      "casual",
      "authentic-food"
    ],
    "showsSoccer": false,
    "openNow": false,
    "priceLevel": 3,
    "rating": 4.1,
    "reviewCount": 530,
    "numberOfScreens": 1,
    "hasProjector": false,
    "hasOutdoorViewing": false,
    "familyFriendly": true,
    "standingRoomFriendly": false,
    "privateEventsAvailable": true,
    "goodForGroups": false,
    "acceptsReservations": true,
    "reservationType": "external_url",
    "reservationUrl": "http://botasf.com/",
    "approximateCapacity": 45,
    "capacityBucket": "30_60",
    "capacityConfidence": "estimated",
    "sourceType": "official_api",
    "sourceName": "Google Places",
    "sourceExternalId": "ChIJH9ELOI6AhYAR9bLZV1xqvAQ",
    "sourceConfidence": 0.92,
    "verificationStatus": "imported",
    "isRealVenue": true,
    "isFeatured": false,
    "isOfficialFanHub": false,
    "gameDayScore": 6.425,
    "fanLikelihoodScore": 7.225,
    "editorialBoost": 0.15,
    "editorialNotes": "Imported from Google Places with name match: tapas.",
    "supporterNotes": "Country assignment verified via name match.",
    "imageUrls": [],
    "createdAt": "2026-04-25T05:33:53.157Z",
    "updatedAt": "2026-04-25T05:49:07.422Z"
  },
  {
    "id": "san-francisco-spain-el-lopo",
    "slug": "san-francisco-spain-el-lopo",
    "name": "El Lopo",
    "description": "El Lopo is a Spain bar in San Francisco.",
    "address": "1327 Polk St, San Francisco, CA 94109, USA",
    "city": "san-francisco",
    "state": "CA",
    "postalCode": "94109",
    "lat": 37.7890509,
    "lng": -122.42057840000001,
    "borough": "Manhattan",
    "neighborhood": "San Francisco",
    "website": "http://elloposf.com/",
    "googleMapsUrl": "https://maps.google.com/?cid=17941003318272758492&g_mp=Cidnb29nbGUubWFwcy5wbGFjZXMudjEuUGxhY2VzLlNlYXJjaFRleHQQAhgEIAA",
    "venueTypes": [
      "bar",
      "restaurant"
    ],
    "associatedCountries": [],
    "likelySupporterCountry": null,
    "venueIntent": "bar_with_tv",
    "cuisineTags": [
      "spain",
      "spain cuisine"
    ],
    "atmosphereTags": [
      "authentic-food",
      "casual",
      "watch-party"
    ],
    "showsSoccer": true,
    "openNow": true,
    "priceLevel": 2,
    "rating": 4.7,
    "reviewCount": 353,
    "numberOfScreens": 3,
    "hasProjector": false,
    "hasOutdoorViewing": true,
    "familyFriendly": false,
    "standingRoomFriendly": true,
    "privateEventsAvailable": true,
    "goodForGroups": true,
    "acceptsReservations": true,
    "reservationType": "external_url",
    "reservationUrl": "http://elloposf.com/",
    "approximateCapacity": 70,
    "capacityBucket": "60_100",
    "capacityConfidence": "estimated",
    "sourceType": "official_api",
    "sourceName": "Google Places",
    "sourceExternalId": "ChIJ9-HrcSOBhYAR3JLAY3Y_-_g",
    "sourceConfidence": 0.92,
    "verificationStatus": "imported",
    "isRealVenue": true,
    "isFeatured": false,
    "isOfficialFanHub": false,
    "gameDayScore": 7.677,
    "fanLikelihoodScore": 8.477,
    "editorialBoost": 0.15,
    "editorialNotes": "Imported from Google Places with type match: spanish_restaurant.",
    "supporterNotes": "Country assignment verified via type match.",
    "imageUrls": [],
    "createdAt": "2026-04-25T05:33:53.157Z",
    "updatedAt": "2026-04-25T05:49:07.422Z"
  },
  {
    "id": "san-francisco-spain-bar-jam-n",
    "slug": "san-francisco-spain-bar-jam-n",
    "name": "Bar Jamón",
    "description": "Bar Jamón is a Spain restaurant in San Francisco.",
    "address": "100 Van Ness Ave, San Francisco, CA 94102, USA",
    "city": "san-francisco",
    "state": "CA",
    "postalCode": "94102",
    "lat": 37.7766802,
    "lng": -122.41922170000001,
    "borough": "Manhattan",
    "neighborhood": "San Francisco",
    "website": "https://www.barjamonatsebastian.com/",
    "googleMapsUrl": "https://maps.google.com/?cid=8156551158993007916&g_mp=Cidnb29nbGUubWFwcy5wbGFjZXMudjEuUGxhY2VzLlNlYXJjaFRleHQQAhgEIAA",
    "venueTypes": [
      "restaurant"
    ],
    "associatedCountries": [],
    "likelySupporterCountry": null,
    "venueIntent": "cultural_restaurant",
    "cuisineTags": [
      "spain",
      "spain cuisine"
    ],
    "atmosphereTags": [
      "casual",
      "authentic-food"
    ],
    "showsSoccer": false,
    "openNow": true,
    "priceLevel": 3,
    "rating": 4.8,
    "reviewCount": 21,
    "numberOfScreens": 1,
    "hasProjector": false,
    "hasOutdoorViewing": false,
    "familyFriendly": true,
    "standingRoomFriendly": false,
    "privateEventsAvailable": true,
    "goodForGroups": false,
    "acceptsReservations": true,
    "reservationType": "external_url",
    "reservationUrl": "https://www.barjamonatsebastian.com/",
    "approximateCapacity": 45,
    "capacityBucket": "30_60",
    "capacityConfidence": "estimated",
    "sourceType": "official_api",
    "sourceName": "Google Places",
    "sourceExternalId": "ChIJD1WpIgCBhYARLDUUWBDkMXE",
    "sourceConfidence": 0.92,
    "verificationStatus": "imported",
    "isRealVenue": true,
    "isFeatured": false,
    "isOfficialFanHub": false,
    "gameDayScore": 5.814,
    "fanLikelihoodScore": 6.614,
    "editorialBoost": 0.15,
    "editorialNotes": "Imported from Google Places with type match: spanish_restaurant.",
    "supporterNotes": "Country assignment verified via type match.",
    "imageUrls": [],
    "createdAt": "2026-04-25T05:33:53.157Z",
    "updatedAt": "2026-04-25T05:49:07.422Z"
  },
  {
    "id": "san-francisco-spain-asiento",
    "slug": "san-francisco-spain-asiento",
    "name": "Asiento",
    "description": "Asiento is a Spain bar in San Francisco.",
    "address": "2730 21st St, San Francisco, CA 94110, USA",
    "city": "san-francisco",
    "state": "CA",
    "postalCode": "94110",
    "lat": 37.7577512,
    "lng": -122.40946289999998,
    "borough": "Manhattan",
    "neighborhood": "San Francisco",
    "website": "http://www.asientosf.com/",
    "googleMapsUrl": "https://maps.google.com/?cid=9160745403802452022&g_mp=Cidnb29nbGUubWFwcy5wbGFjZXMudjEuUGxhY2VzLlNlYXJjaFRleHQQAhgEIAA",
    "venueTypes": [
      "bar",
      "restaurant"
    ],
    "associatedCountries": [],
    "likelySupporterCountry": null,
    "venueIntent": "bar_with_tv",
    "cuisineTags": [
      "spain",
      "spain cuisine"
    ],
    "atmosphereTags": [
      "authentic-food",
      "casual",
      "watch-party"
    ],
    "showsSoccer": true,
    "openNow": true,
    "priceLevel": 2,
    "rating": 4.6,
    "reviewCount": 533,
    "numberOfScreens": 3,
    "hasProjector": false,
    "hasOutdoorViewing": true,
    "familyFriendly": false,
    "standingRoomFriendly": true,
    "privateEventsAvailable": true,
    "goodForGroups": true,
    "acceptsReservations": true,
    "reservationType": "external_url",
    "reservationUrl": "http://www.asientosf.com/",
    "approximateCapacity": 70,
    "capacityBucket": "60_100",
    "capacityConfidence": "estimated",
    "sourceType": "official_api",
    "sourceName": "Google Places",
    "sourceExternalId": "ChIJ64HRTjZ-j4ARNgBwt2iBIX8",
    "sourceConfidence": 0.92,
    "verificationStatus": "imported",
    "isRealVenue": true,
    "isFeatured": false,
    "isOfficialFanHub": false,
    "gameDayScore": 7.6499999999999995,
    "fanLikelihoodScore": 8.45,
    "editorialBoost": 0.15,
    "editorialNotes": "Imported from Google Places with type match: spanish_restaurant.",
    "supporterNotes": "Country assignment verified via type match.",
    "imageUrls": [],
    "createdAt": "2026-04-25T05:33:53.157Z",
    "updatedAt": "2026-04-25T05:49:07.422Z"
  }
]