[
  {
    "id": "toronto-haiti-rhum-corner",
    "slug": "toronto-haiti-rhum-corner",
    "name": "Rhum Corner",
    "description": "Rhum Corner in Toronto for Haiti.",
    "address": "926 Dundas St W, Toronto, ON M6J 1W3, Canada",
    "city": "Toronto",
    "state": "ON",
    "postalCode": "",
    "lat": 43.6510331,
    "lng": -79.4132377,
    "borough": "Manhattan",
    "neighborhood": "Toronto",
    "website": "http://rhumcorner.com/",
    "googleMapsUrl": "https://maps.google.com/?cid=7730972298657507867&g_mp=Cidnb29nbGUubWFwcy5wbGFjZXMudjEuUGxhY2VzLlNlYXJjaFRleHQQAhgEIAA",
    "venueTypes": [
      "bar",
      "restaurant"
    ],
    "associatedCountries": [
      "haiti"
    ],
    "likelySupporterCountry": "haiti",
    "venueIntent": "sports_bar",
    "cuisineTags": [
      "haiti",
      "haiti cuisine"
    ],
    "atmosphereTags": [
      "watch-party",
      "loud",
      "big-groups"
    ],
    "showsSoccer": true,
    "openNow": false,
    "priceLevel": 2,
    "rating": 4.7,
    "reviewCount": 735,
    "numberOfScreens": 5,
    "hasProjector": true,
    "hasOutdoorViewing": true,
    "familyFriendly": false,
    "standingRoomFriendly": true,
    "privateEventsAvailable": true,
    "goodForGroups": true,
    "acceptsReservations": true,
    "reservationType": "external_url",
    "reservationUrl": "http://rhumcorner.com/",
    "approximateCapacity": 70,
    "capacityBucket": "60_100",
    "capacityConfidence": "estimated",
    "sourceType": "official_api",
    "sourceName": "Google Places",
    "sourceExternalId": "ChIJE9VYR-U0K4gRG6rdXVjuSWs",
    "sourceConfidence": 0.92,
    "verificationStatus": "imported",
    "isRealVenue": true,
    "isFeatured": true,
    "isOfficialFanHub": false,
    "gameDayScore": 8.265,
    "fanLikelihoodScore": 9.065000000000001,
    "editorialBoost": 0.15,
    "imageUrls": [],
    "createdAt": "2026-04-24T04:14:47.364Z",
    "updatedAt": "2026-04-24T04:14:47.364Z"
  },
  {
    "id": "toronto-haiti-the-dock-ellis",
    "slug": "toronto-haiti-the-dock-ellis",
    "name": "The Dock Ellis",
    "description": "The Dock Ellis in Toronto for Haiti.",
    "address": "1280 Dundas St W, Toronto, ON M6J 1X7, Canada",
    "city": "Toronto",
    "state": "ON",
    "postalCode": "",
    "lat": 43.6496158,
    "lng": -79.42531819999999,
    "borough": "Manhattan",
    "neighborhood": "Toronto",
    "website": "http://thedockellis.com/",
    "googleMapsUrl": "https://maps.google.com/?cid=1718649790424021816&g_mp=Cidnb29nbGUubWFwcy5wbGFjZXMudjEuUGxhY2VzLlNlYXJjaFRleHQQAhgEIAA",
    "venueTypes": [
      "bar",
      "supporter_club"
    ],
    "associatedCountries": [
      "haiti"
    ],
    "likelySupporterCountry": "haiti",
    "venueIntent": "sports_bar",
    "cuisineTags": [
      "haiti",
      "haiti cuisine"
    ],
    "atmosphereTags": [
      "watch-party",
      "loud",
      "big-groups"
    ],
    "showsSoccer": true,
    "openNow": true,
    "priceLevel": 2,
    "rating": 4.4,
    "reviewCount": 539,
    "numberOfScreens": 5,
    "hasProjector": true,
    "hasOutdoorViewing": true,
    "familyFriendly": false,
    "standingRoomFriendly": true,
    "privateEventsAvailable": true,
    "goodForGroups": true,
    "acceptsReservations": true,
    "reservationType": "external_url",
    "reservationUrl": "http://thedockellis.com/",
    "approximateCapacity": 120,
    "capacityBucket": "100_200",
    "capacityConfidence": "estimated",
    "sourceType": "official_api",
    "sourceName": "Google Places",
    "sourceExternalId": "ChIJl0FCoPg0K4gROPuF6-De2Rc",
    "sourceConfidence": 0.92,
    "verificationStatus": "imported",
    "isRealVenue": true,
    "isFeatured": false,
    "isOfficialFanHub": false,
    "gameDayScore": 7.92,
    "fanLikelihoodScore": 8.72,
    "editorialBoost": 0.15,
    "imageUrls": [],
    "createdAt": "2026-04-24T04:14:47.364Z",
    "updatedAt": "2026-04-24T04:14:47.364Z"
  },
  {
    "id": "toronto-haiti-garden-bar-bodega",
    "slug": "toronto-haiti-garden-bar-bodega",
    "name": "Garden Bar & Bodega",
    "description": "Garden Bar & Bodega in Toronto for Haiti.",
    "address": "1173 Dundas St E, Toronto, ON M4M 3P1, Canada",
    "city": "Toronto",
    "state": "ON",
    "postalCode": "",
    "lat": 43.66450280000001,
    "lng": -79.3417205,
    "borough": "Manhattan",
    "neighborhood": "Toronto",
    "website": "http://www.gardenbar.to/",
    "googleMapsUrl": "https://maps.google.com/?cid=11818754374571746814&g_mp=Cidnb29nbGUubWFwcy5wbGFjZXMudjEuUGxhY2VzLlNlYXJjaFRleHQQAhgEIAA",
    "venueTypes": [
      "bar",
      "restaurant",
      "cafe"
    ],
    "associatedCountries": [
      "haiti"
    ],
    "likelySupporterCountry": "haiti",
    "venueIntent": "sports_bar",
    "cuisineTags": [
      "haiti",
      "haiti cuisine"
    ],
    "atmosphereTags": [
      "watch-party",
      "loud",
      "big-groups"
    ],
    "showsSoccer": true,
    "openNow": true,
    "priceLevel": 2,
    "rating": 4.9,
    "reviewCount": 157,
    "numberOfScreens": 5,
    "hasProjector": true,
    "hasOutdoorViewing": true,
    "familyFriendly": true,
    "standingRoomFriendly": true,
    "privateEventsAvailable": true,
    "goodForGroups": true,
    "acceptsReservations": true,
    "reservationType": "external_url",
    "reservationUrl": "http://www.gardenbar.to/",
    "approximateCapacity": 70,
    "capacityBucket": "60_100",
    "capacityConfidence": "estimated",
    "sourceType": "official_api",
    "sourceName": "Google Places",
    "sourceExternalId": "ChIJC1X9pAvL1IkR_mXxN3ymBKQ",
    "sourceConfidence": 0.92,
    "verificationStatus": "imported",
    "isRealVenue": true,
    "isFeatured": false,
    "isOfficialFanHub": false,
    "gameDayScore": 7.623,
    "fanLikelihoodScore": 8.423,
    "editorialBoost": 0.15,
    "imageUrls": [],
    "createdAt": "2026-04-24T04:14:47.364Z",
    "updatedAt": "2026-04-24T04:14:47.364Z"
  },
  {
    "id": "toronto-haiti-elephant-castle",
    "slug": "toronto-haiti-elephant-castle",
    "name": "Elephant & Castle",
    "description": "Elephant & Castle in Toronto for Haiti.",
    "address": "212 King St W, Toronto, ON M5H 1K5, Canada",
    "city": "Toronto",
    "state": "ON",
    "postalCode": "",
    "lat": 43.647632,
    "lng": -79.3864375,
    "borough": "Manhattan",
    "neighborhood": "Toronto",
    "website": "https://www.elephantcastle.com/en/locations/on/toronto/212-king-street-west",
    "googleMapsUrl": "https://maps.google.com/?cid=94848761902399650&g_mp=Cidnb29nbGUubWFwcy5wbGFjZXMudjEuUGxhY2VzLlNlYXJjaFRleHQQAhgEIAA",
    "venueTypes": [
      "restaurant"
    ],
    "associatedCountries": [
      "haiti"
    ],
    "likelySupporterCountry": "haiti",
    "venueIntent": "cultural_dining",
    "cuisineTags": [
      "haiti",
      "haiti cuisine"
    ],
    "atmosphereTags": [
      "casual",
      "authentic-food"
    ],
    "showsSoccer": false,
    "openNow": true,
    "priceLevel": 3,
    "rating": 4.2,
    "reviewCount": 4249,
    "numberOfScreens": 1,
    "hasProjector": false,
    "hasOutdoorViewing": false,
    "familyFriendly": true,
    "standingRoomFriendly": false,
    "privateEventsAvailable": true,
    "goodForGroups": false,
    "acceptsReservations": true,
    "reservationType": "external_url",
    "reservationUrl": "https://www.elephantcastle.com/en/locations/on/toronto/212-king-street-west",
    "approximateCapacity": 45,
    "capacityBucket": "30_60",
    "capacityConfidence": "estimated",
    "sourceType": "official_api",
    "sourceName": "Google Places",
    "sourceExternalId": "ChIJv0YHUcs0K4gRogCUSHL4UAE",
    "sourceConfidence": 0.92,
    "verificationStatus": "imported",
    "isRealVenue": true,
    "isFeatured": false,
    "isOfficialFanHub": false,
    "gameDayScore": 6.640000000000001,
    "fanLikelihoodScore": 7.44,
    "editorialBoost": 0.15,
    "imageUrls": [],
    "createdAt": "2026-04-24T04:14:47.364Z",
    "updatedAt": "2026-04-24T04:14:47.364Z"
  },
  {
    "id": "toronto-haiti-everyside-social-eatery-taphouse",
    "slug": "toronto-haiti-everyside-social-eatery-taphouse",
    "name": "Everyside - Social Eatery & Taphouse",
    "description": "Everyside - Social Eatery & Taphouse in Toronto for Haiti.",
    "address": "120 Adelaide St W #100, Toronto, ON M5H 1T1, Canada",
    "city": "Toronto",
    "state": "ON",
    "postalCode": "",
    "lat": 43.6497295,
    "lng": -79.3832339,
    "borough": "Manhattan",
    "neighborhood": "Toronto",
    "website": "https://www.drinkeveryside.com/",
    "googleMapsUrl": "https://maps.google.com/?cid=18239122841084033602&g_mp=Cidnb29nbGUubWFwcy5wbGFjZXMudjEuUGxhY2VzLlNlYXJjaFRleHQQAhgEIAA",
    "venueTypes": [
      "restaurant"
    ],
    "associatedCountries": [
      "haiti"
    ],
    "likelySupporterCountry": "haiti",
    "venueIntent": "cultural_dining",
    "cuisineTags": [
      "haiti",
      "haiti cuisine"
    ],
    "atmosphereTags": [
      "casual",
      "authentic-food"
    ],
    "showsSoccer": false,
    "openNow": true,
    "priceLevel": 3,
    "rating": 4.8,
    "reviewCount": 442,
    "numberOfScreens": 1,
    "hasProjector": false,
    "hasOutdoorViewing": false,
    "familyFriendly": true,
    "standingRoomFriendly": false,
    "privateEventsAvailable": true,
    "goodForGroups": false,
    "acceptsReservations": true,
    "reservationType": "external_url",
    "reservationUrl": "https://www.drinkeveryside.com/",
    "approximateCapacity": 45,
    "capacityBucket": "30_60",
    "capacityConfidence": "estimated",
    "sourceType": "official_api",
    "sourceName": "Google Places",
    "sourceExternalId": "ChIJwflzdkM1K4gRQvqGxZZhHv0",
    "sourceConfidence": 0.92,
    "verificationStatus": "imported",
    "isRealVenue": true,
    "isFeatured": false,
    "isOfficialFanHub": false,
    "gameDayScore": 7.33,
    "fanLikelihoodScore": 8.13,
    "editorialBoost": 0.15,
    "imageUrls": [],
    "createdAt": "2026-04-24T04:14:47.364Z",
    "updatedAt": "2026-04-24T04:14:47.364Z"
  },
  {
    "id": "toronto-haiti-saint-john-s-tavern",
    "slug": "toronto-haiti-saint-john-s-tavern",
    "name": "Saint John's Tavern",
    "description": "Saint John's Tavern in Toronto for Haiti.",
    "address": "117 John St, Toronto, ON M5V 2E2, Canada",
    "city": "Toronto",
    "state": "ON",
    "postalCode": "",
    "lat": 43.6481345,
    "lng": -79.3901668,
    "borough": "Manhattan",
    "neighborhood": "Toronto",
    "website": "http://www.saintjohnstavern.com/",
    "googleMapsUrl": "https://maps.google.com/?cid=11427554153544216441&g_mp=Cidnb29nbGUubWFwcy5wbGFjZXMudjEuUGxhY2VzLlNlYXJjaFRleHQQAhgEIAA",
    "venueTypes": [
      "bar",
      "restaurant"
    ],
    "associatedCountries": [
      "haiti"
    ],
    "likelySupporterCountry": "haiti",
    "venueIntent": "sports_bar",
    "cuisineTags": [
      "haiti",
      "haiti cuisine"
    ],
    "atmosphereTags": [
      "watch-party",
      "loud",
      "big-groups"
    ],
    "showsSoccer": true,
    "openNow": true,
    "priceLevel": 2,
    "rating": 4.4,
    "reviewCount": 720,
    "numberOfScreens": 5,
    "hasProjector": true,
    "hasOutdoorViewing": true,
    "familyFriendly": false,
    "standingRoomFriendly": true,
    "privateEventsAvailable": true,
    "goodForGroups": true,
    "acceptsReservations": true,
    "reservationType": "external_url",
    "reservationUrl": "http://www.saintjohnstavern.com/",
    "approximateCapacity": 70,
    "capacityBucket": "60_100",
    "capacityConfidence": "estimated",
    "sourceType": "official_api",
    "sourceName": "Google Places",
    "sourceExternalId": "ChIJPSpa4NI1K4gRee-K9fTTlp4",
    "sourceConfidence": 0.92,
    "verificationStatus": "imported",
    "isRealVenue": true,
    "isFeatured": false,
    "isOfficialFanHub": false,
    "gameDayScore": 7.92,
    "fanLikelihoodScore": 8.72,
    "editorialBoost": 0.15,
    "imageUrls": [],
    "createdAt": "2026-04-24T04:14:47.364Z",
    "updatedAt": "2026-04-24T04:14:47.364Z"
  },
  {
    "id": "toronto-haiti-hoops-sports-bar-grill",
    "slug": "toronto-haiti-hoops-sports-bar-grill",
    "name": "Hoops Sports Bar & Grill",
    "description": "Hoops Sports Bar & Grill in Toronto for Haiti.",
    "address": "125 Bremner Blvd, Toronto, ON M5J 3A8, Canada",
    "city": "Toronto",
    "state": "ON",
    "postalCode": "",
    "lat": 43.6424282,
    "lng": -79.3829744,
    "borough": "Manhattan",
    "neighborhood": "Toronto",
    "website": "https://www.hoopssportsbar.com/",
    "googleMapsUrl": "https://maps.google.com/?cid=4539731837828969688&g_mp=Cidnb29nbGUubWFwcy5wbGFjZXMudjEuUGxhY2VzLlNlYXJjaFRleHQQAhgEIAA",
    "venueTypes": [
      "bar",
      "restaurant"
    ],
    "associatedCountries": [
      "haiti"
    ],
    "likelySupporterCountry": "haiti",
    "venueIntent": "sports_bar",
    "cuisineTags": [
      "haiti",
      "haiti cuisine"
    ],
    "atmosphereTags": [
      "watch-party",
      "loud",
      "big-groups"
    ],
    "showsSoccer": true,
    "openNow": true,
    "priceLevel": 2,
    "rating": 3.3,
    "reviewCount": 2384,
    "numberOfScreens": 5,
    "hasProjector": true,
    "hasOutdoorViewing": true,
    "familyFriendly": false,
    "standingRoomFriendly": true,
    "privateEventsAvailable": true,
    "goodForGroups": true,
    "acceptsReservations": true,
    "reservationType": "external_url",
    "reservationUrl": "https://www.hoopssportsbar.com/",
    "approximateCapacity": 70,
    "capacityBucket": "60_100",
    "capacityConfidence": "estimated",
    "sourceType": "official_api",
    "sourceName": "Google Places",
    "sourceExternalId": "ChIJ0-3L_tQ0K4gR2LRT0Q1eAD8",
    "sourceConfidence": 0.92,
    "verificationStatus": "imported",
    "isRealVenue": true,
    "isFeatured": false,
    "isOfficialFanHub": false,
    "gameDayScore": 7,
    "fanLikelihoodScore": 7.8,
    "editorialBoost": 0.15,
    "imageUrls": [],
    "createdAt": "2026-04-24T04:14:47.364Z",
    "updatedAt": "2026-04-24T04:14:47.364Z"
  },
  {
    "id": "toronto-haiti-tropical-venue",
    "slug": "toronto-haiti-tropical-venue",
    "name": "Tropical Venue",
    "description": "Tropical Venue in Toronto for Haiti.",
    "address": "1776 St Clair Ave W, Toronto, ON M6N 1J3, Canada",
    "city": "Toronto",
    "state": "ON",
    "postalCode": "",
    "lat": 43.674098699999995,
    "lng": -79.46146420000001,
    "borough": "Manhattan",
    "neighborhood": "Toronto",
    "googleMapsUrl": "https://maps.google.com/?cid=8109348177210000116&g_mp=Cidnb29nbGUubWFwcy5wbGFjZXMudjEuUGxhY2VzLlNlYXJjaFRleHQQAhgEIAA",
    "venueTypes": [
      "bar",
      "restaurant",
      "supporter_club"
    ],
    "associatedCountries": [
      "haiti"
    ],
    "likelySupporterCountry": "haiti",
    "venueIntent": "sports_bar",
    "cuisineTags": [
      "haiti",
      "haiti cuisine"
    ],
    "atmosphereTags": [
      "watch-party",
      "loud",
      "big-groups"
    ],
    "showsSoccer": true,
    "openNow": true,
    "priceLevel": 2,
    "rating": 4.5,
    "reviewCount": 65,
    "numberOfScreens": 5,
    "hasProjector": true,
    "hasOutdoorViewing": true,
    "familyFriendly": false,
    "standingRoomFriendly": true,
    "privateEventsAvailable": false,
    "goodForGroups": true,
    "acceptsReservations": false,
    "reservationType": "none",
    "approximateCapacity": 120,
    "capacityBucket": "100_200",
    "capacityConfidence": "estimated",
    "sourceType": "official_api",
    "sourceName": "Google Places",
    "sourceExternalId": "ChIJTdbpC5s1K4gR9EKQtjMxinA",
    "sourceConfidence": 0.92,
    "verificationStatus": "imported",
    "isRealVenue": true,
    "isFeatured": false,
    "isOfficialFanHub": false,
    "gameDayScore": 6.795,
    "fanLikelihoodScore": 7.595,
    "editorialBoost": 0.15,
    "imageUrls": [],
    "createdAt": "2026-04-24T04:14:47.364Z",
    "updatedAt": "2026-04-24T04:14:47.364Z"
  },
  {
    "id": "toronto-haiti-loose-moose-antler-room",
    "slug": "toronto-haiti-loose-moose-antler-room",
    "name": "Loose Moose / Antler Room",
    "description": "Loose Moose / Antler Room in Toronto for Haiti.",
    "address": "146 Front St W, Toronto, ON M5J 1G2, Canada",
    "city": "Toronto",
    "state": "ON",
    "postalCode": "",
    "lat": 43.6452275,
    "lng": -79.38395600000001,
    "borough": "Manhattan",
    "neighborhood": "Toronto",
    "website": "https://theloosemoose.ca/",
    "googleMapsUrl": "https://maps.google.com/?cid=8606202924272108652&g_mp=Cidnb29nbGUubWFwcy5wbGFjZXMudjEuUGxhY2VzLlNlYXJjaFRleHQQAhgEIAA",
    "venueTypes": [
      "bar",
      "restaurant"
    ],
    "associatedCountries": [
      "haiti"
    ],
    "likelySupporterCountry": "haiti",
    "venueIntent": "sports_bar",
    "cuisineTags": [
      "haiti",
      "haiti cuisine"
    ],
    "atmosphereTags": [
      "watch-party",
      "loud",
      "big-groups"
    ],
    "showsSoccer": true,
    "openNow": true,
    "priceLevel": 2,
    "rating": 4.3,
    "reviewCount": 7662,
    "numberOfScreens": 5,
    "hasProjector": true,
    "hasOutdoorViewing": true,
    "familyFriendly": false,
    "standingRoomFriendly": true,
    "privateEventsAvailable": true,
    "goodForGroups": true,
    "acceptsReservations": true,
    "reservationType": "external_url",
    "reservationUrl": "https://theloosemoose.ca/",
    "approximateCapacity": 70,
    "capacityBucket": "60_100",
    "capacityConfidence": "estimated",
    "sourceType": "official_api",
    "sourceName": "Google Places",
    "sourceExternalId": "ChIJWYMdhdM0K4gRbMQqRvZfb3c",
    "sourceConfidence": 0.92,
    "verificationStatus": "imported",
    "isRealVenue": true,
    "isFeatured": false,
    "isOfficialFanHub": false,
    "gameDayScore": 7.805,
    "fanLikelihoodScore": 8.605,
    "editorialBoost": 0.15,
    "imageUrls": [],
    "createdAt": "2026-04-24T04:14:47.364Z",
    "updatedAt": "2026-04-24T04:14:47.364Z"
  },
  {
    "id": "toronto-haiti-the-queen-beaver-public-house",
    "slug": "toronto-haiti-the-queen-beaver-public-house",
    "name": "The Queen & Beaver Public House",
    "description": "The Queen & Beaver Public House in Toronto for Haiti.",
    "address": "35 Elm St, Toronto, ON M5G 1H1, Canada",
    "city": "Toronto",
    "state": "ON",
    "postalCode": "",
    "lat": 43.6574024,
    "lng": -79.3833882,
    "borough": "Manhattan",
    "neighborhood": "Toronto",
    "website": "http://queenandbeaverpub.ca/",
    "googleMapsUrl": "https://maps.google.com/?cid=2281454144781055959&g_mp=Cidnb29nbGUubWFwcy5wbGFjZXMudjEuUGxhY2VzLlNlYXJjaFRleHQQAhgEIAA",
    "venueTypes": [
      "bar",
      "restaurant",
      "supporter_club"
    ],
    "associatedCountries": [
      "haiti"
    ],
    "likelySupporterCountry": "haiti",
    "venueIntent": "sports_bar",
    "cuisineTags": [
      "haiti",
      "haiti cuisine"
    ],
    "atmosphereTags": [
      "watch-party",
      "loud",
      "big-groups"
    ],
    "showsSoccer": true,
    "openNow": false,
    "priceLevel": 2,
    "rating": 4.4,
    "reviewCount": 2789,
    "numberOfScreens": 5,
    "hasProjector": true,
    "hasOutdoorViewing": true,
    "familyFriendly": false,
    "standingRoomFriendly": true,
    "privateEventsAvailable": true,
    "goodForGroups": true,
    "acceptsReservations": true,
    "reservationType": "external_url",
    "reservationUrl": "http://queenandbeaverpub.ca/",
    "approximateCapacity": 120,
    "capacityBucket": "100_200",
    "capacityConfidence": "estimated",
    "sourceType": "official_api",
    "sourceName": "Google Places",
    "sourceExternalId": "ChIJgZGqX8o0K4gR13cE_3RaqR8",
    "sourceConfidence": 0.92,
    "verificationStatus": "imported",
    "isRealVenue": true,
    "isFeatured": false,
    "isOfficialFanHub": false,
    "gameDayScore": 7.92,
    "fanLikelihoodScore": 8.72,
    "editorialBoost": 0.15,
    "imageUrls": [],
    "createdAt": "2026-04-24T04:14:47.364Z",
    "updatedAt": "2026-04-24T04:14:47.364Z"
  }
]